Workbook

Sheet Sheet1
A1: cust_id | B1: status cust_id | C1: Classificação Atual | D1: deals group on wpp? | E1: link | F1: Tipo Link | G1: URL Corrigida
A2: 84848607 | B2: Confirmado | C2: KAM - top 1000 | D2: Sim | E2: https://chat.whatsapp.com/LBBRUqRFNeQElNvFBIvGiD | F2: Link Quebrado
A3: 94733098 | B3: Confirmado | C3: KAM - top 1000 | D3: Sim | E3: https://chat.whatsapp.com/IR0gCURtqgZAJGne6meFbh | F3: Grupo
A4: 224168003 | B4: Confirmado | C4: KAM - top 1000 | D4: Sim | E4: https://www.whatsapp.com/channel/0029VamngXq6xCSIPEEtlw01 https://www.whatsapp.com/channel/0029VatvEAm3LdQSgVnsaV3X https://chat.whatsapp.com/JVIE5k7qfd3J3UDC0iotAD | F4: Misto
A5: 288063877 | B5: Confirmado | C5: KAM - top 1000 | D5: Sim | E5: https://chat.whatsapp.com/FYshNVla9hcBWbSoIwfGm3 | F5: Grupo
A6: 473343832 | B6: Confirmado | C6: KAM - top 1000 | D6: Sim | E6: https://chat.whatsapp.com/KvP3btvte3j6t7w7m9Q6h7 | F6: Grupo
A7: 1299080285 | B7: Confirmado | C7: KAM - top 1000 | D7: Sim | E7: https://achadinhosimperdiveis.com.br/achadinho-grupo | F7: Grupo
A8: 1334764746 | B8: Confirmado | C8: KAM - top 1000 | D8: Sim | E8: https://chat.whatsapp.com/EuscaPvDB4t2rTAC1gSG05 | F8: Grupo
A9: 1374758175 | B9: Confirmado | C9: KAM - top 1000 | D9: Sim | E9: https://sndflw.com/i/grupospromotop | F9: Grupo
A10: 1399249654 | B10: Confirmado | C10: KAM - top 1000 | D10: Sim | E10: l.instagram.com/?u=https%3A%2F%2Fwhatsapp.com%2Fchannel%2F0029Vb6XAspJ3juxxcp3UH1i%3Ffbclid%3DPAZXh0bgNhZW0CMTEAAadBdK77zRWg5sZktionHSexH5za-rLvFztWXI3mhVIBOTXbG2kRXJWPnC65VQ_aem_ke8foGBPJza_P58nBxfqqg&e=AT10GY-UGrn6D2i2SinDN0XgE7irReo8I-g3uQY097DN-WeG7aoFXDZopMQ0OwgnczwdqC8il0xWCJUkQDB1U0YEBdUUeir4QcCgDOg9xg | F10: Canal
A11: 1428402957 | B11: Confirmado | C11: KAM - top 1000 | D11: Sim | E11: https://chat.whatsapp.com/Itr0HHBK6I7Gwt1oJ7FyUy?mode=wwc | F11: Grupo
A12: 1438016577 | B12: Confirmado | C12: KAM - top 1000 | D12: Sim | E12: https://chat.whatsapp.com/ELd5ipGU0HnGR2nsuZzCOw | F12: Grupo
A13: 1463526269 | B13: Confirmado | C13: KAM - top 1000 | D13: Sim | E13: https://chat.whatsapp.com/EfbYI7XUWZA1KcK89zgygE?mode=ems_copy_t | F13: Grupo
... A33: 2359144247 | B33: Confirmado | C33: KAM - top 1000 | D33: Sim | E33: https://chat.whatsapp.com/Lvt6ezs2Fz6ItqKyCW6JE6?mode=ems_copy_c&fbclid=PAZXh0bgNhZW0CMTEAAaecVIipIqzPHpM9TWnQt9z5lLbf8yw0MVN9vTjW7esIEjh9DNIm2Xb8mIN4kw_aem__bvkExuwYQzmobqnHbOmOA | F33: Grupo
A34: 1813105314 | B34: Confirmado | C34: KAM - top 1000 | D34: Sim | E34: https://i.sendflow.pro/invite/GrupoDaGaaby?utm_id=1344207247310791_v2_s01_e1001&fbclid=PAZXh0bgNhZW0CMTEAAadI0I5Xxqj2d3cC6QNpTKVu3GVOoWRpweL6ejiN9j8h_70LcVId0QaDQyabog_aem_OHbflDNFGlrp5Hutuk-rCQ | F34: Grupo | G34: https://chat.whatsapp.com/FFBssTAsJUe5S1fdCPjfjU
A35: 1377978276 | B35: Confirmado | C35: KAM - top 1000 | D35: Sim | E35: https://chat.whatsapp.com/Ks3048s1gRjGzqfnbOmRKs | F35: Grupo
A36: 1494770433 | B36: Confirmado | C36: KAM - top 1000 | D36: Sim | E36: https://chat.whatsapp.com/Bye3jMn7cOa7YkeymQIZIC?mode=wwt | F36: Grupo
A37: 1478707361 | B37: Confirmado | C37: KAM - top 1000 | D37: Sim | E37: https://chat.whatsapp.com/GANhutgr55J95N65Xb6Lk3 | F37: Grupo
A38: 512970471 | B38: Confirmado | C38: KAM - top 1000 | D38: Sim | E38: https://chat.whatsapp.com/D6vTMhtpTji4R4oJ1oBcB2 | F38: Grupo
A39: 1408672391 | B39: Confirmado | C39: KAM - top 1000 | D39: Sim | E39: https://chat.whatsapp.com/HlzrhZslJCZ6YVTSRDI71M?fbclid=PAZXh0bgNhZW0CMTEAAaeHCVvc7x51MYFXyqM5U8Vp142hYcrnX9m3TEYGypZ49CY9XKSMc1l0jIISvQ_aem_SWfxcvpL11OpZOE0WOljRg | F39: Grupo
A40: 1446956733 | B40: Confirmado | C40: KAM - top 1000 | D40: Sim | E40: https://chat.whatsapp.com/DSeLEmy3Ccg2cQIQu0PZIg | F40: Grupo
A41: 226046758 | B41: Confirmado | C41: KAM - top 1000 | D41: Sim | E41: https://chat.whatsapp.com/JMfX31vfU1BBh6cf7R0Uqo | F41: Grupo
A42: 150242200 | B42: Confirmado | C42: KAM - top 1000 | D42: Sim | E42: https://chat.whatsapp.com/DFpRm2RkKfFGpYfqLxWcAo | F42: Grupo
A43: 269721398 | B43: Confirmado | C43: KAM - top 1000 | D43: Sim | E43: https://chat.whatsapp.com/FKCP03nC7DLKYr1sonRws9 | F43: Grupo
A44: 1516990091 | B44: Confirmado | C44: KAM - top 1000 | D44: Sim | E44: https://chat.whatsapp.com/FJpxwCaPLyO6VJjgSQPRRo?mode=ac_t | F44: Grupo
A45: 379432988 | B45: Confirmado | C45: KAM - top 1000 | D45: Sim | E45: http://chat.whatsapp.com/FuRrPRMeses2RqaTpBagwf https://chat.whatsapp.com/LiJjq9uEt07Hf6EXIc4LQp | F45: Grupo
A46: 1433577301 | B46: Confirmado | C46: KAM - top 1000 | D46: Sim | E46: https://t.me/promotom | F46: Conversa
... A56: 1541281221 | B56: Confirmado | C56: KAM - top 1000 | D56: Sim | E56: https://t.me/hardmoboficial?fbclid=PAZXh0bgNhZW0CMTEAAad91QlFMoxqd5UJjboP1N62cWtANiGM8E-vBGNaFAYTv22PVy_IgmIAYP2ncA_aem_dIDit8IE-_yP-KhZd8qrvw | F56: Telegram
A57: 618183409 | B57: Confirmado | C57: KAM - top 1000 | D57: Sim | E57: app.gruposinteligentes.com/r/achadosdaccarol | F57: Grupo | G57: https://chat.whatsapp.com/JUkT4DzEq8E2qKDq8gUQNV
A58: 1954038151 | B58: Confirmado | C58: KAM - top 1000 | D58: Sim | E58: https://chat.whatsapp.com/GUgEwbuk86aJDdyJfLsSQ3 | F58: Grupo
A59: 744048622 | B59: Confirmado | C59: KAM - top 1000 | D59: Sim | E59: https://chat.whatsapp.com/BZpAuh2smnSBgAMWUIr8it | F59: Grupo
A60: 79019768 | B60: Confirmado | C60: KAM - top 1000 | D60: Sim | E60: https://chat.whatsapp.com/CMPA3hBbXmSBg7aEoHcdAc | F60: Grupo
A61: 521028663 | B61: Confirmado | C61: KAM - top 1000 | D61: Sim | E61: https://chat.whatsapp.com/JHaBQhjiioN4q54FVbHTv0 | F61: Grupo
A62: 1578049413 | B62: Confirmado | C62: KAM - top 1000 | D62: Sim | E62: https://t.me/outletblackfriday?fbclid=PAZXh0bgNhZW0CMTEAAac47Msicc8FXyO3GJEJp7W7OpkgNlER3DQHosVikFjue5nnEBRylCDqCn4shg_aem_6FHXolLGMvNQDjPKiROTIw | F62: Telegram
A63: 1442794904 | B63: Confirmado | C63: KAM - top 1000 | D63: Sim | E63: https://t.me/economizanderson?fbclid=PAZXh0bgNhZW0CMTEAAaef6d27dw2ja87QTtQO_MnMQVpnvTWC5XNp7DI3yRcBqkCTEbNwFlDejv1mCg_aem_HUyi1kmKQpZ1Kp3U_gcqJQ | F63: Telegram
A64: 136554975 | B64: Confirmado | C64: KAM - top 1000 | D64: Sim | E64: https://chat.whatsapp.com/CCbeOEcw45ZIS7Du8dZchQ | F64: Grupo
A65: 1550052320 | B65: Confirmado | C65: KAM - top 1000 | D65: Sim | E65: https://chat.whatsapp.com/K41Nfk48Mid9cAN7OA1V3K | F65: Grupo
A66: 92792646 | B66: Confirmado | C66: KAM - top 1000 | D66: Sim | E66: https://chat.whatsapp.com/Hi4wsoxm8oyDgk09a0zpEW?mode=wwc | F66: Grupo
A67: 192874049 | B67: Confirmado | C67: KAM - top 1000 | D67: Sim | E67: https://t.me/guigatudo?fbclid=PAZXh0bgNhZW0CMTEAAacBjHWdgbtIiHfb7eVYEP7x7VJoopp-_VAx_bvrD99Tkr_EbdNI1HnzpiKmUQ_aem_4ywXVHc8170ntvYwuqnUjA | F67: Telegram
A68: 481509072 | B68: Confirmado | C68: KAM - top 1000 | D68: Sim | E68: https://chat.whatsapp.com/Hjr3f7J3jCB5dxUy4DqPpl?mode=wwc | F68: Grupo
A69: 303223557 | B69: Confirmado | C69: KAM - top 1000 | D69: Sim | E69: https://chat.whatsapp.com/FBdHps1zuMO6gkstqu6jfT | F69: Link Quebrado
... A239: 136382088 | B239: Confirmado | C239: MElIpro | D239: Sim | E239: https://chat.whatsapp.com/H9dxNyPzbWSLGTqbp2ov2A | F239: Grupo
A240: 142704481 | B240: Confirmado | C240: MElIpro | D240: Sim | E240: https://tr.ee/zHxv780O0c | F240: Grupo | G240: https://chat.whatsapp.com/JfArtqAk9VfD6b8ZOz4Qyc
A241: 238863610 | B241: Confirmado | C241: MElIpro | D241: Sim | E241: https://t.me/puranostalgiashopee?fbclid=PAZXh0bgNhZW0CMTEAAacHsDRA407f-3YbwbdXQ515qdVDc_a9HhRaZMxjkAO5HJSYC71mMeZvUe119w_aem_eb7-lRjFuTmMF-EyXuTQHQ | F241: Telegram
A242: 303120592 | B242: Confirmado | C242: MElIpro | D242: Sim | E242: https://chat.whatsapp.com/BehJuWtRQk30H2wXFFd9HU | F242: Grupo
A243: 375366165 | B243: Confirmado | C243: MElIpro | D243: Sim | E243: https://chat.whatsapp.com/DaLYRjgWYRIKypTbQT0FVS?fbclid=PAZXh0bgNhZW0CMTEAAaf6ydk2xafcnYx5kWspQGGWQoW8udj1rh-hHHu0_UN26bKYazlt_oCrJNW1Rw_aem_POcZlhZOz76KfcKi8PHglw | F243: Grupo
A244: 484123181 | B244: Confirmado | C244: MElIpro | D244: Sim | E244: https://chat.whatsapp.com/FpIsHgK4X6jAIPtb6K9Ifl?mode=ac_t | F244: Grupo
A245: 695303632 | B245: Confirmado | C245: MElIpro | D245: Sim | E245: https://chat.whatsapp.com/D5OdEreGcV30WhGShSqJOW?fbclid=PAZXh0bgNhZW0CMTEAAacvaAj8yuh04D4lQAsSHAfsASl4Ftm0Sq04E_yq-zodh1MxGjtDS8zfsEDFsg_aem_1kmj9nkK5CiJZ9i8_E27cw | F245: Grupo
A246: 699370117 | B246: Confirmado | C246: MElIpro | D246: Sim | E246: https://chat.whatsapp.com/K6DAzAvNur4IabDyHeb2Y3?mode=ems_copy_t&fbclid=PAZXh0bgNhZW0CMTEAAacToXVWdlXegf-9uNBLuKK3RyUvY57YE47UVMht5jf6djL4-hogWGMtjeF_uQ_aem_6YlLmsP4JR_GGkadUzr48w | F246: Grupo
A247: 799601634 | B247: Confirmado | C247: MElIpro | D247: Sim | E247: https://chat.whatsapp.com/GcFEsEGhAywB0Bp1wtpfrH | F247: Grupo
A248: 1063208859 | B248: Confirmado | C248: MElIpro | D248: Sim | E248: https://chat.whatsapp.com/HUIQoCtX7af4mhEE7bEIhw | F248: Grupo
A249: 1351369312 | B249: Confirmado | C249: MElIpro | D249: Sim | E249: https://chat.whatsapp.com/C98f1fCpVK2B3QLwXYwACQ | F249: Grupo
A250: 1428326558 | B250: Confirmado | C250: MElIpro | D250: Sim | E250: https://chat.whatsapp.com/BgdoWxdm0RWKZVQDrhVTk8 | F250: Grupo
A251: 1457793802 | B251: Confirmado | C251: MElIpro | D251: Sim | E251: https://chat.whatsapp.com/FQSjEe3qC804trDpyaG05h | F251: Grupo
A252: 1676657192 | B252: Confirmado | C252: MElIpro | D252: Sim | E252: https://chat.whatsapp.com/HByXpAYMbzP8TkQrfp5PTS?fbclid=PAZXh0bgNhZW0CMTEAAaf04i_YzjO1AXgzF_Qa8GvlhsJmzQnpKooeQ9LyacXUSWELmkTXefzdWomwHQ_aem_rYZWDI3F3TPOl6lHF36T0A | F252: Grupo
... A293: 61249096 | B293: Confirmado | C293: MElIpro | D293: Sim | E293: https://chat.whatsapp.com/LCQhtszftoPKeLJBtgc363?fbclid=PAZXh0bgNhZW0CMTEAAadgwAmqiZr2wGoSL7doa6wcTtHPlcHEJFDWIRbqx20jHI7VQg5B4thEXhL2Qw_aem_k1LF_AIe_LEFw0YeFOHsUg | F293: Grupo
A294: 594475926 | B294: Confirmado | C294: MElIpro | D294: Sim | E294: https://i.sendflow.pro/invite/pAtaG706VFv2j2gIIMuO | F294: Grupo | G294: https://chat.whatsapp.com/EuPOVBxriny1fYPaTfWKkW
A295: 62381440 | B295: Confirmado | C295: MElIpro | D295: Sim | E295: https://chat.whatsapp.com/HE0qDdyC4woF3ZDPTQ6fQd?fbclid=PAZXh0bgNhZW0CMTEAAadH4Ahx_sAi7erue56Wv4WojpNl2PsA5JXRRyWNH99SwHXzfnLl2gm4sGuyHA_aem_6EUJ1nULHcvem9oNRbiiVA | F295: Grupo
A296: 264616806 | B296: Confirmado | C296: MElIpro | D296: Sim | E296: https://chat.whatsapp.com/Gz4jmOCoP7FIKn3LrDvMzd | F296: Grupo
A297: 606319384 | B297: Confirmado | C297: MElIpro | D297: Sim | E297: https://chat.whatsapp.com/F7NJkwakRiNHYCvqm99YP7 | F297: Grupo
A298: 204139460 | B298: Confirmado | C298: MElIpro | D298: Sim | E298: https://www.whatsapp.com/channel/0029Vb62JAnI1rclRh8Fp930 | F298: Canal
A299: 636693914 | B299: Confirmado | C299: MElIpro | D299: Sim | E299: https://chat.whatsapp.com/JY4qQRWdVEVCSDRNHSxYTH?fbclid=PAZXh0bgNhZW0CMTEAAaeg0l0X6hlocE3UMuo-a6EOZtou2YASbTbuihkhELjQZDvNAchpyvbbuZ95Uw_aem_7Guu2J9CoNct-achcfUZmQ | F299: Grupo
A300: 1096521350 | B300: Confirmado | C300: MElIpro | D300: Sim | E300: https://chat.whatsapp.com/H0tkGH3KzjGAG7zsR42QxZ?utm_medium=social&utm_source=linktree&utm_campaign=entrar+no+grupo+do+whatsapp+ | F300: Grupo
A301: 1080122761 | B301: Confirmado | C301: MElIpro | D301: Sim | E301: https://chat.whatsapp.com/Gu55Qpt3baS0ETcRirO33M | F301: Grupo
A302: 225367126 | B302: Confirmado | C302: MElIpro | D302: Sim | E302: https://www.whatsapp.com/channel/0029VafETHjHLHQPMhDXoU1U | F302: Canal
A303: 1106563292 | B303: Confirmado | C303: MElIpro | D303: Sim | E303: https://chat.whatsapp.com/Kgw6HiTuPAeDDfIsotIrln | F303: Grupo
A304: 727809733 | B304: Confirmado | C304: MElIpro | D304: Sim | E304: https://chat.whatsapp.com/CwWuRmKxOXfJSidEqrrisv?fbclid=PAZXh0bgNhZW0CMTEAAadBvZ13lJ5w8OXUV2iNHHuLunGzi48P0n0uW43YWkQCmp8Y97b4Vi9DFfoh3g_aem_LaujT_DV5KYuQuRloVcimA | F304: Grupo
A305: 255589674 | B305: Confirmado | C305: MElIpro | D305: Sim | E305: https://chat.whatsapp.com/DZd3F34NqlOBrOG22YiB1F?fbclid=PAZXh0bgNhZW0CMTEAAafCeMVDTlArPVKftbd_AnpIUkNDuLR1FhiB1E7st3b4QF0D2wZktyNtJT_XxA_aem_XFKounzmmzUJR56ZH9ztbg | F305: Grupo
A306: 1751948527 | B306: Confirmado | C306: MElIpro | D306: Sim | E306: https://www.whatsapp.com/channel/0029VbB6mjdGJP8NfREt291s?fbclid=PAZXh0bgNhZW0CMTEAAacUrIUAu80gM-L8IdPImGEN2xiNxF4tMLxdbvRw1e4cHVc_Q6Tgj--LQvCf4w_aem_ro_CqntEy4TIzns9BUHkXg | F306: Canal
... A368: 751415749 | B368: Confirmado | C368: MElIpro | D368: Sim | E368: https://chat.whatsapp.com/I52E8CM6aBsCYPQwIsYinG | F368: Grupo
A369: 238910194 | B369: Confirmado | C369: MElIpro | D369: Sim | E369: https://curt.link/grupovipdeofertas | F369: Grupo | G369: https://chat.whatsapp.com/FpExACiIrkOJDO4TPoqJjO
A370: 209463598 | B370: Confirmado | C370: MElIpro | D370: Sim | E370: https://chat.whatsapp.com/BhqmU2xmZexKpoAV46f7eg | F370: Grupo
A371: 488851324 | B371: Pendente | C371: top KAM Cross/Tech | D371: Sim
A372: 2490611911 | B372: Pendente | C372: top KAM Cross/Tech | D372: Sim
A373: 1477497679 | B373: Pendente | C373: top KAM Cross/Tech | D373: Sim
A374: 555414187 | B374: Pendente | C374: top KAM Cross/Tech | D374: Sim
A375: 1236298302 | B375: Pendente | C375: top KAM Cross/Tech | D375: Sim
A376: 1245410086 | B376: Pendente | C376: top KAM Cross/Tech | D376: Sim
A377: 1231808348 | B377: Pendente | C377: top KAM Cross/Tech | D377: Sim
A378: 1406524799 | B378: Pendente | C378: top KAM Cross/Tech | D378: Sim
A379: 1464475202 | B379: Pendente | C379: top KAM Cross/Tech | D379: Sim
A380: 1342859483 | B380: Pendente | C380: top KAM Cross/Tech | D380: Sim
A381: 1317961778 | B381: Pendente | C381: top KAM Cross/Tech | D381: Sim
A382: 1286635153 | B382: Pendente | C382: top KAM Cross/Tech | D382: Sim
... A430: 1427776750 | B430: Pendente | C430: top KAM Cross/Tech | D430: Sim

Sheet Tech e Cross
A1: cus_cust_id_aff | B1: aff_name | C1: Check | D1: rede 1 | E1: rede 2 | F1: grupo
A2: 488851324 | B2: promosdodia | C2: {=IFERROR(_xludf.XLOOKUP(A2,Sheet1!A:A,Sheet1!B:B),"Não")} -> Não | D2: {=_xludf.XLOOKUP(A2,import!A:A,import!C:C)} -> #NAME? | E2: {=_xludf.XLOOKUP(A2,import!A:A,import!E:E)} -> #NAME?
A3: 2490611911 | B3: promozonevip | C3: {=IFERROR(_xludf.XLOOKUP(A3,Sheet1!A:A,Sheet1!B:B),"Não")} -> Não | D3: {=_xludf.XLOOKUP(A3,import!A:A,import!C:C)} -> #NAME? | E3: {=_xludf.XLOOKUP(A3,import!A:A,import!E:E)} -> #NAME? | F3: https://www.whatsapp.com/channel/0029VbBuyGKCxoAyO2Utji3k
A4: 1477497679 | B4: minutoreview | C4: {=IFERROR(_xludf.XLOOKUP(A4,Sheet1!A:A,Sheet1!B:B),"Não")} -> Não | D4: {=_xludf.XLOOKUP(A4,import!A:A,import!C:C)} -> #NAME? | E4: {=_xludf.XLOOKUP(A4,import!A:A,import!E:E)} -> #NAME? | F4: https://t.me/heroidapromo
A5: 555414187 | B5: Xetdaspromocoes | C5: {=IFERROR(_xludf.XLOOKUP(A5,Sheet1!A:A,Sheet1!B:B),"Não")} -> Não | D5: {=_xludf.XLOOKUP(A5,import!A:A,import!C:C)} -> #NAME? | E5: {=_xludf.XLOOKUP(A5,import!A:A,import!E:E)} -> #NAME? | F5: https://tr.ee/uRb7a25vid
A6: 1236298302 | B6: jersu | C6: {=IFERROR(_xludf.XLOOKUP(A6,Sheet1!A:A,Sheet1!B:B),"Não")} -> Não | D6: {=_xludf.XLOOKUP(A6,import!A:A,import!C:C)} -> #NAME? | E6: {=_xludf.XLOOKUP(A6,import!A:A,import!E:E)} -> #NAME? | F6: https://chat.whatsapp.com/DEvLKnMXcn11I4VonM1GbH
A7: 1245410086 | B7: tukemperial | C7: {=IFERROR(_xludf.XLOOKUP(A7,Sheet1!A:A,Sheet1!B:B),"Não")} -> Não | D7: {=_xludf.XLOOKUP(A7,import!A:A,import!C:C)} -> #NAME? | E7: {=_xludf.XLOOKUP(A7,import!A:A,import!E:E)} -> #NAME?
A8: 1231808348 | B8: gesiel | C8: {=IFERROR(_xludf.XLOOKUP(A8,Sheet1!A:A,Sheet1!B:B),"Não")} -> Não | D8: {=_xludf.XLOOKUP(A8,import!A:A,import!C:C)} -> #NAME? | E8: {=_xludf.XLOOKUP(A8,import!A:A,import!E:E)} -> #NAME? | F8: https://www.whatsapp.com/channel/0029VaEPqqBDOQIUTTOCMg1l
A9: 1406524799 | B9: Toptech | C9: {=IFERROR(_xludf.XLOOKUP(A9,Sheet1!A:A,Sheet1!B:B),"Não")} -> Não | D9: {=_xludf.XLOOKUP(A9,import!A:A,import!C:C)} -> #NAME? | E9: {=_xludf.XLOOKUP(A9,import!A:A,import!E:E)} -> #NAME?
A10: 1464475202 | B10: joaopsx | C10: {=IFERROR(_xludf.XLOOKUP(A10,Sheet1!A:A,Sheet1!B:B),"Não")} -> Não | D10: {=_xludf.XLOOKUP(A10,import!A:A,import!C:C)} -> #NAME? | E10: {=_xludf.XLOOKUP(A10,import!A:A,import!E:E)} -> #NAME? | F10: https://www.whatsapp.com/channel/0029Va9lrS5GufIu669tIy13
A11: 1342859483 | B11: abelhando | C11: {=IFERROR(_xludf.XLOOKUP(A11,Sheet1!A:A,Sheet1!B:B),"Não")} -> Não | D11: {=_xludf.XLOOKUP(A11,import!A:A,import!C:C)} -> #NAME? | E11: {=_xludf.XLOOKUP(A11,import!A:A,import!E:E)} -> #NAME? | F11: https://chat.whatsapp.com/K6CTXebMZ0eJMX8B8uIiA1
A12: 1317961778 | B12: thautec | C12: {=IFERROR(_xludf.XLOOKUP(A12,Sheet1!A:A,Sheet1!B:B),"Não")} -> Não | D12: {=_xludf.XLOOKUP(A12,import!A:A,import!C:C)} -> #NAME? | E12: {=_xludf.XLOOKUP(A12,import!A:A,import!E:E)} -> #NAME? | F12: https://www.whatsapp.com/channel/0029Val8yoECHDyoi2TgYt1z
A13: 1286635153 | B13: economizei | C13: {=IFERROR(_xludf.XLOOKUP(A13,Sheet1!A:A,Sheet1!B:B),"Não")} -> Não | D13: {=_xludf.XLOOKUP(A13,import!A:A,import!C:C)} -> #NAME? | E13: {=_xludf.XLOOKUP(A13,import!A:A,import!E:E)} -> #NAME?
A14: 1445776663 | B14: JCAPUBLICIDADE | C14: {=IFERROR(_xludf.XLOOKUP(A14,Sheet1!A:A,Sheet1!B:B),"Não")} -> Não | D14: {=_xludf.XLOOKUP(A14,import!A:A,import!C:C)} -> #NAME? | E14: {=_xludf.XLOOKUP(A14,import!A:A,import!E:E)} -> #NAME? | F14: https://chat.whatsapp.com/D5RX0sZReSDISIJG4WsZ38
A15: 1211756872 | B15: lipe | C15: {=IFERROR(_xludf.XLOOKUP(A15,Sheet1!A:A,Sheet1!B:B),"Não")} -> Não | D15: {=_xludf.XLOOKUP(A15,import!A:A,import!C:C)} -> #NAME? | E15: {=_xludf.XLOOKUP(A15,import!A:A,import!E:E)} -> #NAME? | F15: https://t.me/lipeofertas
A16: 1207675246 | B16: canalrodrigomoreira | C16: {=IFERROR(_xludf.XLOOKUP(A16,Sheet1!A:A,Sheet1!B:B),"Não")} -> Não | D16: {=_xludf.XLOOKUP(A16,import!A:A,import!C:C)} -> #NAME? | E16: {=_xludf.XLOOKUP(A16,import!A:A,import!E:E)} -> #NAME? | F16: https://chat.whatsapp.com/DYL3yM8t1Qx5ZIRJR3PUh7?mode=ems_copy_t
A17: 1422846329 | B17: coelhonojapo | C17: {=IFERROR(_xludf.XLOOKUP(A17,Sheet1!A:A,Sheet1!B:B),"Não")} -> Não | D17: {=_xludf.XLOOKUP(A17,import!A:A,import!C:C)} -> #NAME? | E17: {=_xludf.XLOOKUP(A17,import!A:A,import!E:E)} -> #NAME? | F17: https://chat.whatsapp.com/Ihx4dPdJUYAAxEmbT1o0Q8
A18: 76331531 | B18: especialistaemti | C18: {=IFERROR(_xludf.XLOOKUP(A18,Sheet1!A:A,Sheet1!B:B),"Não")} -> Não | D18: {=_xludf.XLOOKUP(A18,import!A:A,import!C:C)} -> #NAME? | E18: {=_xludf.XLOOKUP(A18,import!A:A,import!E:E)} -> #NAME? | F18: https://chat.whatsapp.com/LRjdSDkp9jd6OOLSCwY5Qm
A19: 1454842874 | B19: promocaozinha | C19: {=IFERROR(_xludf.XLOOKUP(A19,Sheet1!A:A,Sheet1!B:B),"Não")} -> Não
A20: 593029712 | B20: pobredasofertas | C20: {=IFERROR(_xludf.XLOOKUP(A20,Sheet1!A:A,Sheet1!B:B),"Não")} -> Não
A21: 207302282 | B21: promos4m | C21: {=IFERROR(_xludf.XLOOKUP(A21,Sheet1!A:A,Sheet1!B:B),"Não")} -> Não
A22: 322502351 | B22: desconto | C22: {=IFERROR(_xludf.XLOOKUP(A22,Sheet1!A:A,Sheet1!B:B),"Não")} -> Não | D22: {=_xludf.XLOOKUP(A22,import!A:A,import!C:C)} -> #NAME? | E22: {=_xludf.XLOOKUP(A22,import!A:A,import!E:E)} -> #NAME? | F22: https://t.me/santostecpromo?fbclid=PAZXh0bgNhZW0CMTEAAaeVb188JbMikBC-pCWnnB-AVUWx8S9YKjN0MyENCabECnWM-Txqf-BfQBDA5A_aem_3uUYjDnj73qTV1TlZ3lA3A
A23: 1375138586 | B23: Canaljptech | C23: {=IFERROR(_xludf.XLOOKUP(A23,Sheet1!A:A,Sheet1!B:B),"Não")} -> Não | D23: {=_xludf.XLOOKUP(A23,import!A:A,import!C:C)} -> #NAME? | E23: {=_xludf.XLOOKUP(A23,import!A:A,import!E:E)} -> #NAME? | F23: https://www.whatsapp.com/channel/0029VaDc0VKATRSg2k5sOb0u
A24: 1366151811 | B24: pcdofafa | C24: {=IFERROR(_xludf.XLOOKUP(A24,Sheet1!A:A,Sheet1!B:B),"Não")} -> Não | D24: {=_xludf.XLOOKUP(A24,import!A:A,import!C:C)} -> #NAME? | E24: {=_xludf.XLOOKUP(A24,import!A:A,import!E:E)} -> #NAME? | F24: https://t.me/fafapromoshorts
A25: 1473563772 | B25: urubupromo | C25: {=IFERROR(_xludf.XLOOKUP(A25,Sheet1!A:A,Sheet1!B:B),"Não")} -> Não
A26: 1249172900 | B26: tttech | C26: {=IFERROR(_xludf.XLOOKUP(A26,Sheet1!A:A,Sheet1!B:B),"Não")} -> Não | D26: {=_xludf.XLOOKUP(A26,import!A:A,import!C:C)} -> #NAME? | E26: {=_xludf.XLOOKUP(A26,import!A:A,import!E:E)} -> #NAME? | F26: https://chat.whatsapp.com/Dq1JEvVMkAmJywEcvLbjB8
A27: 1478114661 | B27: peguepromo | C27: {=IFERROR(_xludf.XLOOKUP(A27,Sheet1!A:A,Sheet1!B:B),"Não")} -> Não | D27: {=_xludf.XLOOKUP(A27,import!A:A,import!C:C)} -> #NAME? | E27: {=_xludf.XLOOKUP(A27,import!A:A,import!E:E)} -> #NAME? | F27: Link quebrado
A28: 1231576803 | B28: inovaleo | C28: {=IFERROR(_xludf.XLOOKUP(A28,Sheet1!A:A,Sheet1!B:B),"Não")} -> Não | D28: {=_xludf.XLOOKUP(A28,import!A:A,import!C:C)} -> #NAME? | E28: {=_xludf.XLOOKUP(A28,import!A:A,import!E:E)} -> #NAME? | F28: https://chat.whatsapp.com/JWySm0bg2QjDJwYKymBRAr?mode=wwt
A29: 1450808630 | B29: agenciarice | C29: {=IFERROR(_xludf.XLOOKUP(A29,Sheet1!A:A,Sheet1!B:B),"Não")} -> Não
A30: 1251879558 | B30: qualnotebook | C30: {=IFERROR(_xludf.XLOOKUP(A30,Sheet1!A:A,Sheet1!B:B),"Não")} -> Não | D30: {=_xludf.XLOOKUP(A30,import!A:A,import!C:C)} -> #NAME? | E30: {=_xludf.XLOOKUP(A30,import!A:A,import!E:E)} -> #NAME? | F30: https://chat.whatsapp.com/J5kJyOeNUjnAOla4kweuk4
A31: 2345017244 | B31: promosinc | C31: {=IFERROR(_xludf.XLOOKUP(A31,Sheet1!A:A,Sheet1!B:B),"Não")} -> Não | D31: {=_xludf.XLOOKUP(A31,import!A:A,import!C:C)} -> #NAME? | E31: {=_xludf.XLOOKUP(A31,import!A:A,import!E:E)} -> #NAME? | F31: Link quebrado
A32: 1453452471 | B32: Daniel Reenlsober | C32: {=IFERROR(_xludf.XLOOKUP(A32,Sheet1!A:A,Sheet1!B:B),"Não")} -> Não | D32: {=_xludf.XLOOKUP(A32,import!A:A,import!C:C)} -> #NAME? | E32: {=_xludf.XLOOKUP(A32,import!A:A,import!E:E)} -> #NAME? | F32: https://www.whatsapp.com/channel/0029Va9QFJGICVfkJA730514
A33: 1161200505 | B33: mastertechjr | C33: {=IFERROR(_xludf.XLOOKUP(A33,Sheet1!A:A,Sheet1!B:B),"Não")} -> Não | D33: {=_xludf.XLOOKUP(A33,import!A:A,import!C:C)} -> #NAME? | E33: {=_xludf.XLOOKUP(A33,import!A:A,import!E:E)} -> #NAME? | F33: https://t.me/mastertechjr?fbclid=PAZXh0bgNhZW0CMTEAAaewxnUciKJdSe5Wco9fLTmBaJM1DHn4eoDmr2swvK0goIkep-9zfI_u-Knyhw_aem_0gcMRKOctBIeWR6jSsQ7RQ
A34: 1374758175 | B34: promotop | C34: {=IFERROR(_xludf.XLOOKUP(A34,Sheet1!A:A,Sheet1!B:B),"Não")} -> Não
A35: 268850426 | B35: jeffrecomenda | C35: {=IFERROR(_xludf.XLOOKUP(A35,Sheet1!A:A,Sheet1!B:B),"Não")} -> Não | D35: {=_xludf.XLOOKUP(A35,import!A:A,import!C:C)} -> #NAME? | E35: {=_xludf.XLOOKUP(A35,import!A:A,import!E:E)} -> #NAME? | F35: https://chat.whatsapp.com/EtM3xhWp5wcFuqkVNdLOL1?mode=ac_t&fbclid=PAZXh0bgNhZW0CMTEAAcvKmLCoRYh1JrXVQa4GIsd0EnkbBnFBQ4AcdQWmNVlGTiH5r-fPAM9WgGJDw_aem_9ZENO9O-OpjiO-ebHt4fdA
A36: 1426808500 | B36: promoimperdivel | C36: {=IFERROR(_xludf.XLOOKUP(A36,Sheet1!A:A,Sheet1!B:B),"Não")} -> Não | D36: {=_xludf.XLOOKUP(A36,import!A:A,import!C:C)} -> #NAME? | E36: {=_xludf.XLOOKUP(A36,import!A:A,import!E:E)} -> #NAME? | F36: https://chat.whatsapp.com/IFJMvDHZc2AIYyGqQcEHqt
A37: 1114585317 | B37: bench promos | C37: {=IFERROR(_xludf.XLOOKUP(A37,Sheet1!A:A,Sheet1!B:B),"Não")} -> Não | D37: {=_xludf.XLOOKUP(A37,import!A:A,import!C:C)} -> #NAME? | E37: {=_xludf.XLOOKUP(A37,import!A:A,import!E:E)} -> #NAME? | F37: https://www.whatsapp.com/channel/0029VbBJP9aDzgTBmNHBd62p?fbclid=PAZXh0bgNhZW0CMTEAAae32tBkLXNaDzwchmglVLXLDmLa4onLEK6UMw4op25Tx7lTcIryD6JcBRv1UA_aem_AznNWot3JZd5_PmBAUTuNg
A38: 1370750164 | B38: switchxz | C38: {=IFERROR(_xludf.XLOOKUP(A38,Sheet1!A:A,Sheet1!B:B),"Não")} -> Não | D38: {=_xludf.XLOOKUP(A38,import!A:A,import!C:C)} -> #NAME? | E38: {=_xludf.XLOOKUP(A38,import!A:A,import!E:E)} -> #NAME? | F38: https://t.me/LinksBrazil?fbclid=PAZXh0bgNhZW0CMTEAAaeCZzCU7ct0adx3XBcqEzD56i_Y-W9K4JavWSlJnENQoakUhv1Jo7E97niWAQ_aem_nKvEHacyctGXjbbgz8Qztw
A39: 251645009 | B39: novosprodutos | C39: {=IFERROR(_xludf.XLOOKUP(A39,Sheet1!A:A,Sheet1!B:B),"Não")} -> Não | D39: {=_xludf.XLOOKUP(A39,import!A:A,import!C:C)} -> #NAME? | E39: {=_xludf.XLOOKUP(A39,import!A:A,import!E:E)} -> #NAME? | F39: https://chat.whatsapp.com/GzuMpKwpGqy89P9YL4cu4x?fbclid=PAZXh0bgNhZW0CMTEAAadtVsUG-QmJI9FtehAWBo4gBDhfKLcva3fXquMK1HL2EKTrPPso_iZwcw83BA_aem_5eHhxYVaRpg-LB_H71RvZg
A40: 263391604 | B40: so_promocoesdodia | C40: {=IFERROR(_xludf.XLOOKUP(A40,Sheet1!A:A,Sheet1!B:B),"Não")} -> Não | D40: {=_xludf.XLOOKUP(A40,import!A:A,import!C:C)} -> #NAME? | E40: {=_xludf.XLOOKUP(A40,import!A:A,import!E:E)} -> #NAME? | F40: https://chat.whatsapp.com/Gw5saEcajBS8p7yf7rgDvf?mode=wwc
A41: 1469910364 | B41: clubedopresidente | C41: {=IFERROR(_xludf.XLOOKUP(A41,Sheet1!A:A,Sheet1!B:B),"Não")} -> Não | D41: {=_xludf.XLOOKUP(A41,import!A:A,import!C:C)} -> #NAME? | E41: {=_xludf.XLOOKUP(A41,import!A:A,import!E:E)} -> #NAME? | F41: Link quebrado
A42: 199199140 | B42: techbr | C42: {=IFERROR(_xludf.XLOOKUP(A42,Sheet1!A:A,Sheet1!B:B),"Não")} -> Não | D42: {=_xludf.XLOOKUP(A42,import!A:A,import!C:C)} -> #NAME? | E42: {=_xludf.XLOOKUP(A42,import!A:A,import!E:E)} -> #NAME? | F42: https://chat.whatsapp.com/DYO3GUfjbNi6ZLlYEBc0hG
A43: 1461583629 | B43: tempromo | C43: {=IFERROR(_xludf.XLOOKUP(A43,Sheet1!A:A,Sheet1!B:B),"Não")} -> Não | D43: {=_xludf.XLOOKUP(A43,import!A:A,import!C:C)} -> #NAME? | E43: {=_xludf.XLOOKUP(A43,import!A:A,import!E:E)} -> #NAME? | F43: https://chat.whatsapp.com/Hsn9IVgrwTWBORxZBTmdSe?mode=wwt
A44: 1159690723 | B44: techmelhores | C44: {=IFERROR(_xludf.XLOOKUP(A44,Sheet1!A:A,Sheet1!B:B),"Não")} -> Não | D44: {=_xludf.XLOOKUP(A44,import!A:A,import!C:C)} -> #NAME? | E44: {=_xludf.XLOOKUP(A44,import!A:A,import!E:E)} -> #NAME?
A45: 1387667693 | B45: descontoemgames | C45: {=IFERROR(_xludf.XLOOKUP(A45,Sheet1!A:A,Sheet1!B:B),"Não")} -> Não | D45: {=_xludf.XLOOKUP(A45,import!A:A,import!C:C)} -> #NAME? | E45: {=_xludf.XLOOKUP(A45,import!A:A,import!E:E)} -> #NAME? | F45: https://www.whatsapp.com/channel/0029Va9PbS9Id7nVKzupxn15
A46: 2389628095 | B46: ofcprominho | C46: {=IFERROR(_xludf.XLOOKUP(A46,Sheet1!A:A,Sheet1!B:B),"Não")} -> Não
A47: 1424070748 | B47: lapromotion | C47: {=IFERROR(_xludf.XLOOKUP(A47,Sheet1!A:A,Sheet1!B:B),"Não")} -> Não | D47: {=_xludf.XLOOKUP(A47,import!A:A,import!C:C)} -> #NAME? | E47: {=_xludf.XLOOKUP(A47,import!A:A,import!E:E)} -> #NAME? | F47: https://www.whatsapp.com/channel/0029VbBZEOzCcW4qg3agqr1H?fbclid=PAZXh0bgNhZW0CMTEAAaeFiwUajifNZ5lSJ33qtqW4O3Ed3OmDUMpe2eW_DFVvenI4Etq-XlhfzEdDcw_aem_5DOqV2dx_s7qAWbX99agvw
A48: 15665498 | B48: kotas | C48: {=IFERROR(_xludf.XLOOKUP(A48,Sheet1!A:A,Sheet1!B:B),"Não")} -> Não | D48: {=_xludf.XLOOKUP(A48,import!A:A,import!C:C)} -> #NAME? | E48: {=_xludf.XLOOKUP(A48,import!A:A,import!E:E)} -> #NAME? | F48: https://chat.whatsapp.com/Hcb23EBqkdo3vYXuuyB8bB?fbclid=PAZXh0bgNhZW0CMTEAAadoR2nM9Yz5VIa_hKSRiNmCnEg4ichC7UL4Cd04m9S8RqZ6hB-s05pfYEyo6w_aem_-lESTKZnYboCxtyqP0CpvA
A49: 521028663 | B49: promotecgames | C49: {=IFERROR(_xludf.XLOOKUP(A49,Sheet1!A:A,Sheet1!B:B),"Não")} -> Não
A50: 150242200 | B50: preguicaofertas | C50: {=IFERROR(_xludf.XLOOKUP(A50,Sheet1!A:A,Sheet1!B:B),"Não")} -> Não
A51: 1446287023 | B51: garimpeiofertas | C51: {=IFERROR(_xludf.XLOOKUP(A51,Sheet1!A:A,Sheet1!B:B),"Não")} -> Não | D51: {=_xludf.XLOOKUP(A51,import!A:A,import!C:C)} -> #NAME? | E51: {=_xludf.XLOOKUP(A51,import!A:A,import!E:E)} -> #NAME? | F51: https://chat.whatsapp.com/JEDsYEWz7z4IE3YJZrqqq1
A52: 268300847 | B52: matheuskise | C52: {=IFERROR(_xludf.XLOOKUP(A52,Sheet1!A:A,Sheet1!B:B),"Não")} -> Não | D52: {=_xludf.XLOOKUP(A52,import!A:A,import!C:C)} -> #NAME? | E52: {=_xludf.XLOOKUP(A52,import!A:A,import!E:E)} -> #NAME? | F52: https://t.me/OlhoNaPROMO
A53: 1427325193 | B53: tabaratasso | C53: {=IFERROR(_xludf.XLOOKUP(A53,Sheet1!A:A,Sheet1!B:B),"Não")} -> Não
A54: 798617488 | B54: Fraguas84 | C54: {=IFERROR(_xludf.XLOOKUP(A54,Sheet1!A:A,Sheet1!B:B),"Não")} -> Não | D54: {=_xludf.XLOOKUP(A54,import!A:A,import!C:C)} -> #NAME? | E54: {=_xludf.XLOOKUP(A54,import!A:A,import!E:E)} -> #NAME? | F54: https://t.me/Fraguas84Oficial
A55: 1342941619 | B55: tecvariedades | C55: {=IFERROR(_xludf.XLOOKUP(A55,Sheet1!A:A,Sheet1!B:B),"Não")} -> Não
A56: 678610452 | B56: samuelf3lipe | C56: {=IFERROR(_xludf.XLOOKUP(A56,Sheet1!A:A,Sheet1!B:B),"Não")} -> Não | D56: {=_xludf.XLOOKUP(A56,import!A:A,import!C:C)} -> #NAME? | E56: {=_xludf.XLOOKUP(A56,import!A:A,import!E:E)} -> #NAME? | F56: https://chat.whatsapp.com/HZwM8xn312XFXh711EG8iQ
A57: 2457362902 | B57: promosdebrother | C57: {=IFERROR(_xludf.XLOOKUP(A57,Sheet1!A:A,Sheet1!B:B),"Não")} -> Não | D57: {=_xludf.XLOOKUP(A57,import!A:A,import!C:C)} -> #NAME? | E57: {=_xludf.XLOOKUP(A57,import!A:A,import!E:E)} -> #NAME?
A58: 44352982 | B58: tjgaming | C58: {=IFERROR(_xludf.XLOOKUP(A58,Sheet1!A:A,Sheet1!B:B),"Não")} -> Não
A59: 330532268 | B59: achadosempromo | C59: {=IFERROR(_xludf.XLOOKUP(A59,Sheet1!A:A,Sheet1!B:B),"Não")} -> Não | D59: {=_xludf.XLOOKUP(A59,import!A:A,import!C:C)} -> #NAME? | E59: {=_xludf.XLOOKUP(A59,import!A:A,import!E:E)} -> #NAME? | F59: Sem link no perfil
A60: 1399249654 | B60: garimpeiros | C60: {=IFERROR(_xludf.XLOOKUP(A60,Sheet1!A:A,Sheet1!B:B),"Não")} -> Não
A61: 149518102 | B61: bizudaspromocoes | C61: {=IFERROR(_xludf.XLOOKUP(A61,Sheet1!A:A,Sheet1!B:B),"Não")} -> Não | D61: {=_xludf.XLOOKUP(A61,import!A:A,import!C:C)} -> #NAME? | E61: {=_xludf.XLOOKUP(A61,import!A:A,import!E:E)} -> #NAME? | F61: https://chat.whatsapp.com/HedUmWn1r3VKHnlZEue8gB?mode=ems_copy_t
A62: 1156310262 | B62: sddescontos | C62: {=IFERROR(_xludf.XLOOKUP(A62,Sheet1!A:A,Sheet1!B:B),"Não")} -> Não
A63: 1420365380 | B63: pincei | C63: {=IFERROR(_xludf.XLOOKUP(A63,Sheet1!A:A,Sheet1!B:B),"Não")} -> Não | D63: {=_xludf.XLOOKUP(A63,import!A:A,import!C:C)} -> #NAME? | E63: {=_xludf.XLOOKUP(A63,import!A:A,import!E:E)} -> #NAME? | F63: https://chat.whatsapp.com/FlTqfDyBFsfEnhg3aNrd2a
A64: 1185718745 | B64: ofertasgamer | C64: {=IFERROR(_xludf.XLOOKUP(A64,Sheet1!A:A,Sheet1!B:B),"Não")} -> Não | D64: {=_xludf.XLOOKUP(A64,import!A:A,import!C:C)} -> #NAME? | E64: {=_xludf.XLOOKUP(A64,import!A:A,import!E:E)} -> #NAME? | F64: https://www.whatsapp.com/channel/0029VaklNp8K5cDK9b5V5L0l
A65: 1434694534 | B65: jogobarato | C65: {=IFERROR(_xludf.XLOOKUP(A65,Sheet1!A:A,Sheet1!B:B),"Não")} -> Não | D65: {=_xludf.XLOOKUP(A65,import!A:A,import!C:C)} -> #NAME? | E65: {=_xludf.XLOOKUP(A65,import!A:A,import!E:E)} -> #NAME?
A66: 1947955373 | B66: guerradealsfit | C66: {=IFERROR(_xludf.XLOOKUP(A66,Sheet1!A:A,Sheet1!B:B),"Não")} -> Não
A67: 2569994453 | B67: OLHADAPROMOS | C67: {=IFERROR(_xludf.XLOOKUP(A67,Sheet1!A:A,Sheet1!B:B),"Não")} -> Não | D67: {=_xludf.XLOOKUP(A67,import!A:A,import!C:C)} -> #NAME? | E67: {=_xludf.XLOOKUP(A67,import!A:A,import!E:E)} -> #NAME?
A68: 1365706499 | B68: peperaio | C68: {=IFERROR(_xludf.XLOOKUP(A68,Sheet1!A:A,Sheet1!B:B),"Não")} -> Não | D68: {=_xludf.XLOOKUP(A68,import!A:A,import!C:C)} -> #NAME? | E68: {=_xludf.XLOOKUP(A68,import!A:A,import!E:E)} -> #NAME? | F68: https://chat.whatsapp.com/GOV8P4YrmjZ3nlehN5jDBZ https://chat.whatsapp.com/K6h8AUFY48X6r3bSRuN41P
A69: 1434918733 | B69: babypromokids | C69: {=IFERROR(_xludf.XLOOKUP(A69,Sheet1!A:A,Sheet1!B:B),"Não")} -> Não | D69: {=_xludf.XLOOKUP(A69,import!A:A,import!C:C)} -> #NAME? | E69: {=_xludf.XLOOKUP(A69,import!A:A,import!E:E)} -> #NAME? | F69: https://chat.whatsapp.com/E4qUixsvh7p5U3oS1RBXrk
A70: 2046114897 | B70: fadadoscupons | C70: {=IFERROR(_xludf.XLOOKUP(A70,Sheet1!A:A,Sheet1!B:B),"Não")} -> Não
A71: 1451916544 | B71: tosemkit | C71: {=IFERROR(_xludf.XLOOKUP(A71,Sheet1!A:A,Sheet1!B:B),"Não")} -> Não | D71: {=_xludf.XLOOKUP(A71,import!A:A,import!C:C)} -> #NAME? | E71: {=_xludf.XLOOKUP(A71,import!A:A,import!E:E)} -> #NAME? | F71: https://chat.whatsapp.com/JQvT3vKC2vj0CscIGMwjAG?mode=wwt
A72: 1482183974 | B72: promohub | C72: {=IFERROR(_xludf.XLOOKUP(A72,Sheet1!A:A,Sheet1!B:B),"Não")} -> Não | D72: {=_xludf.XLOOKUP(A72,import!A:A,import!C:C)} -> #NAME? | E72: {=_xludf.XLOOKUP(A72,import!A:A,import!E:E)} -> #NAME? | F72: https://chat.whatsapp.com/KbiC4HyAPgZ5c0B4YZtX5N
A73: 2351879503 | B73: br20250326135135 | C73: {=IFERROR(_xludf.XLOOKUP(A73,Sheet1!A:A,Sheet1!B:B),"Não")} -> Não | D73: {=_xludf.XLOOKUP(A73,import!A:A,import!C:C)} -> #NAME? | E73: {=_xludf.XLOOKUP(A73,import!A:A,import!E:E)} -> #NAME? | F73: Sem link no perfil
A74: 1514602500 | B74: recomendou | C74: {=IFERROR(_xludf.XLOOKUP(A74,Sheet1!A:A,Sheet1!B:B),"Não")} -> Não | D74: {=_xludf.XLOOKUP(A74,import!A:A,import!C:C)} -> #NAME? | E74: {=_xludf.XLOOKUP(A74,import!A:A,import!E:E)} -> #NAME? | F74: Sem link
A75: 1457441247 | B75: cupons | C75: {=IFERROR(_xludf.XLOOKUP(A75,Sheet1!A:A,Sheet1!B:B),"Não")} -> Não
A76: 200355621 | B76: ultreyamarketing | C76: {=IFERROR(_xludf.XLOOKUP(A76,Sheet1!A:A,Sheet1!B:B),"Não")} -> Não
A77: 152436288 | B77: gugaaprova | C77: {=IFERROR(_xludf.XLOOKUP(A77,Sheet1!A:A,Sheet1!B:B),"Não")} -> Não
A78: 2313173800 | B78: ofertinhasecia | C78: {=IFERROR(_xludf.XLOOKUP(A78,Sheet1!A:A,Sheet1!B:B),"Não")} -> Não | D78: {=_xludf.XLOOKUP(A78,import!A:A,import!C:C)} -> #NAME? | E78: {=_xludf.XLOOKUP(A78,import!A:A,import!E:E)} -> #NAME?
A79: 547239300 | B79: d6news | C79: {=IFERROR(_xludf.XLOOKUP(A79,Sheet1!A:A,Sheet1!B:B),"Não")} -> Não | D79: {=_xludf.XLOOKUP(A79,import!A:A,import!C:C)} -> #NAME? | E79: {=_xludf.XLOOKUP(A79,import!A:A,import!E:E)} -> #NAME? | F79: https://chat.whatsapp.com/JG3b8ccRQQtHsNnIwRcvE1
A80: 1427776750 | B80: leotecnodia | C80: {=IFERROR(_xludf.XLOOKUP(A80,Sheet1!A:A,Sheet1!B:B),"Não")} -> Não | D80: {=_xludf.XLOOKUP(A80,import!A:A,import!C:C)} -> #NAME? | E80: {=_xludf.XLOOKUP(A80,import!A:A,import!E:E)} -> #NAME?

Sheet import
A1: =IFERROR(__xludf.DUMMYFUNCTION("IMPORTRANGE(""https://docs.google.com/spreadsheets/d/10g4G0kCjCDd_ICa4_A1YPT2Qy7lcMrhzmtXWv-RZ8rU/edit?gid=968273440#gid=968273440"",""Gestão Carteira!A2:B2000"")"),"cus_cust_id_aff") -> cus_cust_id_aff | B1: =IFERROR(__xludf.DUMMYFUNCTION("""COMPUTED_VALUE"""),"aff_name") -> aff_name | C1: =IFERROR(__xludf.DUMMYFUNCTION("IMPORTRANGE(""https://docs.google.com/spreadsheets/d/10g4G0kCjCDd_ICa4_A1YPT2Qy7lcMrhzmtXWv-RZ8rU/edit?gid=968273440#gid=968273440"",""Gestão Carteira!AM2:AP2000"")"),"Qual seu Instagram?") -> Qual seu Instagram? | D1: =IFERROR(__xludf.DUMMYFUNCTION("""COMPUTED_VALUE"""),"Quantos seguidores você tem no Instagram?") -> Quantos seguidores você tem no Instagram? | E1: =IFERROR(__xludf.DUMMYFUNCTION("""COMPUTED_VALUE"""),"Qual seu perfil no TikTok?") -> Qual seu perfil no TikTok? | F1: =IFERROR(__xludf.DUMMYFUNCTION("""COMPUTED_VALUE"""),"Quantos seguidores você tem no TikTok?") -> Quantos seguidores você tem no TikTok?
A2: =IFERROR(__xludf.DUMMYFUNCTION("""COMPUTED_VALUE"""),488851324) -> 488851324 | B2: =IFERROR(__xludf.DUMMYFUNCTION("""COMPUTED_VALUE"""),"promosdodia") -> promosdodia | C2: =IFERROR(__xludf.DUMMYFUNCTION("""COMPUTED_VALUE"""),"") | D2: =IFERROR(__xludf.DUMMYFUNCTION("""COMPUTED_VALUE"""),"") | E2: =IFERROR(__xludf.DUMMYFUNCTION("""COMPUTED_VALUE"""),"") | F2: =IFERROR(__xludf.DUMMYFUNCTION("""COMPUTED_VALUE"""),"")
A3: =IFERROR(__xludf.DUMMYFUNCTION("""COMPUTED_VALUE"""),2490611911) -> 2490611911 | B3: =IFERROR(__xludf.DUMMYFUNCTION("""COMPUTED_VALUE"""),"promozonevip") -> promozonevip | C3: =IFERROR(__xludf.DUMMYFUNCTION("""COMPUTED_VALUE"""),"https://www.instagram.com/eusoubarone?igsh=cWVvOXQydzdseW15") -> https://www.instagram.com/eusoubarone?igsh=cWVvOXQydzdseW15 | D3: =IFERROR(__xludf.DUMMYFUNCTION("""COMPUTED_VALUE"""),4000000) -> 4000000
A4: =IFERROR(__xludf.DUMMYFUNCTION("""COMPUTED_VALUE"""),1477497679) -> 1477497679 | B4: =IFERROR(__xludf.DUMMYFUNCTION("""COMPUTED_VALUE"""),"minutoreview") -> minutoreview | C4: =IFERROR(__xludf.DUMMYFUNCTION("""COMPUTED_VALUE"""),"https://www.instagram.com/heroidapromo/") -> https://www.instagram.com/heroidapromo/ | D4: =IFERROR(__xludf.DUMMYFUNCTION("""COMPUTED_VALUE"""),147000) -> 147000
A5: =IFERROR(__xludf.DUMMYFUNCTION("""COMPUTED_VALUE"""),555414187) -> 555414187 | B5: =IFERROR(__xludf.DUMMYFUNCTION("""COMPUTED_VALUE"""),"Xetdaspromocoes") -> Xetdaspromocoes | C5: =IFERROR(__xludf.DUMMYFUNCTION("""COMPUTED_VALUE"""),"https://x.com/xetdaspromocoes") -> https://x.com/xetdaspromocoes | D5: =IFERROR(__xludf.DUMMYFUNCTION("""COMPUTED_VALUE"""),500000) -> 500000
A6: =IFERROR(__xludf.DUMMYFUNCTION("""COMPUTED_VALUE"""),1236298302) -> 1236298302 | B6: =IFERROR(__xludf.DUMMYFUNCTION("""COMPUTED_VALUE"""),"jersu") -> jersu | C6: =IFERROR(__xludf.DUMMYFUNCTION("""COMPUTED_VALUE"""),"https://www.instagram.com/jeersu") -> https://www.instagram.com/jeersu | D6: =IFERROR(__xludf.DUMMYFUNCTION("""COMPUTED_VALUE"""),171000) -> 171000 | E6: =IFERROR(__xludf.DUMMYFUNCTION("""COMPUTED_VALUE"""),"https://www.tiktok.com/@jersu") -> https://www.tiktok.com/@jersu | F6: =IFERROR(__xludf.DUMMYFUNCTION("""COMPUTED_VALUE"""),114000) -> 114000
A7: =IFERROR(__xludf.DUMMYFUNCTION("""COMPUTED_VALUE"""),1245410086) -> 1245410086 | B7: =IFERROR(__xludf.DUMMYFUNCTION("""COMPUTED_VALUE"""),"tukemperial") -> tukemperial | C7: =IFERROR(__xludf.DUMMYFUNCTION("""COMPUTED_VALUE"""),"") | D7: =IFERROR(__xludf.DUMMYFUNCTION("""COMPUTED_VALUE"""),"") | E7: =IFERROR(__xludf.DUMMYFUNCTION("""COMPUTED_VALUE"""),"") | F7: =IFERROR(__xludf.DUMMYFUNCTION("""COMPUTED_VALUE"""),"")
A8: =IFERROR(__xludf.DUMMYFUNCTION("""COMPUTED_VALUE"""),1231808348) -> 1231808348 | B8: =IFERROR(__xludf.DUMMYFUNCTION("""COMPUTED_VALUE"""),"gesiel") -> gesiel | C8: =IFERROR(__xludf.DUMMYFUNCTION("""COMPUTED_VALUE"""),"https://www.instagram.com/gesieltaveira/") -> https://www.instagram.com/gesieltaveira/ | D8: =IFERROR(__xludf.DUMMYFUNCTION("""COMPUTED_VALUE"""),388000) -> 388000 | E8: =IFERROR(__xludf.DUMMYFUNCTION("""COMPUTED_VALUE"""),"https://www.tiktok.com/@gesieltaveira") -> https://www.tiktok.com/@gesieltaveira | F8: =IFERROR(__xludf.DUMMYFUNCTION("""COMPUTED_VALUE"""),267600) -> 267600
A9: =IFERROR(__xludf.DUMMYFUNCTION("""COMPUTED_VALUE"""),1406524799) -> 1406524799 | B9: =IFERROR(__xludf.DUMMYFUNCTION("""COMPUTED_VALUE"""),"Toptech") -> Toptech | C9: =IFERROR(__xludf.DUMMYFUNCTION("""COMPUTED_VALUE"""),"") | D9: =IFERROR(__xludf.DUMMYFUNCTION("""COMPUTED_VALUE"""),"") | E9: =IFERROR(__xludf.DUMMYFUNCTION("""COMPUTED_VALUE"""),"") | F9: =IFERROR(__xludf.DUMMYFUNCTION("""COMPUTED_VALUE"""),"")
A10: =IFERROR(__xludf.DUMMYFUNCTION("""COMPUTED_VALUE"""),1464475202) -> 1464475202 | B10: =IFERROR(__xludf.DUMMYFUNCTION("""COMPUTED_VALUE"""),"joaopsx") -> joaopsx | C10: =IFERROR(__xludf.DUMMYFUNCTION("""COMPUTED_VALUE"""),"https://www.instagram.com/joao_psx/") -> https://www.instagram.com/joao_psx/ | D10: =IFERROR(__xludf.DUMMYFUNCTION("""COMPUTED_VALUE"""),30000) -> 30000 | E10: =IFERROR(__xludf.DUMMYFUNCTION("""COMPUTED_VALUE"""),"https://www.tiktok.com/@joaopsx") -> https://www.tiktok.com/@joaopsx | F10: =IFERROR(__xludf.DUMMYFUNCTION("""COMPUTED_VALUE"""),15000) -> 15000
A11: =IFERROR(__xludf.DUMMYFUNCTION("""COMPUTED_VALUE"""),1342859483) -> 1342859483 | B11: =IFERROR(__xludf.DUMMYFUNCTION("""COMPUTED_VALUE"""),"abelhando") -> abelhando | C11: =IFERROR(__xludf.DUMMYFUNCTION("""COMPUTED_VALUE"""),"https://www.instagram.com/vrltecnologia/") -> https://www.instagram.com/vrltecnologia/ | D11: =IFERROR(__xludf.DUMMYFUNCTION("""COMPUTED_VALUE"""),3000) -> 3000 | E11: =IFERROR(__xludf.DUMMYFUNCTION("""COMPUTED_VALUE"""),"https://www.tiktok.com/@vrltecnologia") -> https://www.tiktok.com/@vrltecnologia | F11: =IFERROR(__xludf.DUMMYFUNCTION("""COMPUTED_VALUE"""),5000) -> 5000
A12: =IFERROR(__xludf.DUMMYFUNCTION("""COMPUTED_VALUE"""),1317961778) -> 1317961778 | B12: =IFERROR(__xludf.DUMMYFUNCTION("""COMPUTED_VALUE"""),"thautec") -> thautec | C12: =IFERROR(__xludf.DUMMYFUNCTION("""COMPUTED_VALUE"""),"www.instagram.com/thautec") -> www.instagram.com/thautec | D12: =IFERROR(__xludf.DUMMYFUNCTION("""COMPUTED_VALUE"""),500000) -> 500000 | E12: =IFERROR(__xludf.DUMMYFUNCTION("""COMPUTED_VALUE"""),"www.tiktok.com/@thautec") -> www.tiktok.com/@thautec | F12: =IFERROR(__xludf.DUMMYFUNCTION("""COMPUTED_VALUE"""),290000) -> 290000
A13: =IFERROR(__xludf.DUMMYFUNCTION("""COMPUTED_VALUE"""),1286635153) -> 1286635153 | B13: =IFERROR(__xludf.DUMMYFUNCTION("""COMPUTED_VALUE"""),"economizei") -> economizei | C13: =IFERROR(__xludf.DUMMYFUNCTION("""COMPUTED_VALUE"""),"") | D13: =IFERROR(__xludf.DUMMYFUNCTION("""COMPUTED_VALUE"""),"") | E13: =IFERROR(__xludf.DUMMYFUNCTION("""COMPUTED_VALUE"""),"") | F13: =IFERROR(__xludf.DUMMYFUNCTION("""COMPUTED_VALUE"""),"")
A14: =IFERROR(__xludf.DUMMYFUNCTION("""COMPUTED_VALUE"""),1445776663) -> 1445776663 | B14: =IFERROR(__xludf.DUMMYFUNCTION("""COMPUTED_VALUE"""),"JCAPUBLICIDADE") -> JCAPUBLICIDADE | C14: =IFERROR(__xludf.DUMMYFUNCTION("""COMPUTED_VALUE"""),"instagram.com/grupotabugado") -> instagram.com/grupotabugado | D14: =IFERROR(__xludf.DUMMYFUNCTION("""COMPUTED_VALUE"""),31500) -> 31500
A15: =IFERROR(__xludf.DUMMYFUNCTION("""COMPUTED_VALUE"""),1211756872) -> 1211756872 | B15: =IFERROR(__xludf.DUMMYFUNCTION("""COMPUTED_VALUE"""),"lipe") -> lipe | C15: =IFERROR(__xludf.DUMMYFUNCTION("""COMPUTED_VALUE"""),"https://www.instagram.com/lipemalestar/") -> https://www.instagram.com/lipemalestar/ | D15: =IFERROR(__xludf.DUMMYFUNCTION("""COMPUTED_VALUE"""),129000) -> 129000 | E15: =IFERROR(__xludf.DUMMYFUNCTION("""COMPUTED_VALUE"""),"https://www.tiktok.com/@lipemalestar") -> https://www.tiktok.com/@lipemalestar | F15: =IFERROR(__xludf.DUMMYFUNCTION("""COMPUTED_VALUE"""),469000) -> 469000
A16: =IFERROR(__xludf.DUMMYFUNCTION("""COMPUTED_VALUE"""),1207675246) -> 1207675246 | B16: =IFERROR(__xludf.DUMMYFUNCTION("""COMPUTED_VALUE"""),"canalrodrigomoreira") -> canalrodrigomoreira | C16: =IFERROR(__xludf.DUMMYFUNCTION("""COMPUTED_VALUE"""),"www.instagram.com/canalrodrigomoreira") -> www.instagram.com/canalrodrigomoreira | D16: =IFERROR(__xludf.DUMMYFUNCTION("""COMPUTED_VALUE"""),34000) -> 34000 | E16: =IFERROR(__xludf.DUMMYFUNCTION("""COMPUTED_VALUE"""),"www.tiktok.com/@canalrodrigomoreira") -> www.tiktok.com/@canalrodrigomoreira | F16: =IFERROR(__xludf.DUMMYFUNCTION("""COMPUTED_VALUE"""),135000) -> 135000
A17: =IFERROR(__xludf.DUMMYFUNCTION("""COMPUTED_VALUE"""),1422846329) -> 1422846329 | B17: =IFERROR(__xludf.DUMMYFUNCTION("""COMPUTED_VALUE"""),"coelhonojapo") -> coelhonojapo | C17: =IFERROR(__xludf.DUMMYFUNCTION("""COMPUTED_VALUE"""),"https://www.instagram.com/rodrigocoelhoc/") -> https://www.instagram.com/rodrigocoelhoc/ | D17: =IFERROR(__xludf.DUMMYFUNCTION("""COMPUTED_VALUE"""),133000) -> 133000 | E17: =IFERROR(__xludf.DUMMYFUNCTION("""COMPUTED_VALUE"""),"https://www.tiktok.com/@rodrigocoelhoc") -> https://www.tiktok.com/@rodrigocoelhoc | F17: =IFERROR(__xludf.DUMMYFUNCTION("""COMPUTED_VALUE"""),70000) -> 70000
A18: =IFERROR(__xludf.DUMMYFUNCTION("""COMPUTED_VALUE"""),76331531) -> 76331531 | B18: =IFERROR(__xludf.DUMMYFUNCTION("""COMPUTED_VALUE"""),"especialistaemti") -> especialistaemti | C18: =IFERROR(__xludf.DUMMYFUNCTION("""COMPUTED_VALUE"""),"instagram.com/especialistaemti") -> instagram.com/especialistaemti | D18: =IFERROR(__xludf.DUMMYFUNCTION("""COMPUTED_VALUE"""),53000) -> 53000 | E18: =IFERROR(__xludf.DUMMYFUNCTION("""COMPUTED_VALUE"""),"tiktok.com/especialistaemti") -> tiktok.com/especialistaemti | F18: =IFERROR(__xludf.DUMMYFUNCTION("""COMPUTED_VALUE"""),10000) -> 10000
A19: =IFERROR(__xludf.DUMMYFUNCTION("""COMPUTED_VALUE"""),1454842874) -> 1454842874 | B19: =IFERROR(__xludf.DUMMYFUNCTION("""COMPUTED_VALUE"""),"promocaozinha") -> promocaozinha | C19: =IFERROR(__xludf.DUMMYFUNCTION("""COMPUTED_VALUE"""),"instagram.com/promocaozinha") -> instagram.com/promocaozinha | D19: =IFERROR(__xludf.DUMMYFUNCTION("""COMPUTED_VALUE"""),2600000) -> 2600000 | E19: =IFERROR(__xludf.DUMMYFUNCTION("""COMPUTED_VALUE"""),"tiktok.com/@promocaozinha") -> tiktok.com/@promocaozinha | F19: =IFERROR(__xludf.DUMMYFUNCTION("""COMPUTED_VALUE"""),200000) -> 200000
A20: =IFERROR(__xludf.DUMMYFUNCTION("""COMPUTED_VALUE"""),593029712) -> 593029712 | B20: =IFERROR(__xludf.DUMMYFUNCTION("""COMPUTED_VALUE"""),"pobredasofertas") -> pobredasofertas | C20: =IFERROR(__xludf.DUMMYFUNCTION("""COMPUTED_VALUE"""),"instagram.com/buscopobres") -> instagram.com/buscopobres | D20: =IFERROR(__xludf.DUMMYFUNCTION("""COMPUTED_VALUE"""),81000) -> 81000 | E20: =IFERROR(__xludf.DUMMYFUNCTION("""COMPUTED_VALUE"""),"tiktok.com/buscopobres") -> tiktok.com/buscopobres | F20: =IFERROR(__xludf.DUMMYFUNCTION("""COMPUTED_VALUE"""),1271) -> 1271
A21: =IFERROR(__xludf.DUMMYFUNCTION("""COMPUTED_VALUE"""),207302282) -> 207302282 | B21: =IFERROR(__xludf.DUMMYFUNCTION("""COMPUTED_VALUE"""),"promos4m") -> promos4m | C21: =IFERROR(__xludf.DUMMYFUNCTION("""COMPUTED_VALUE"""),"https://www.instagram.com/promos4m/") -> https://www.instagram.com/promos4m/ | D21: =IFERROR(__xludf.DUMMYFUNCTION("""COMPUTED_VALUE"""),13745) -> 13745 | E21: =IFERROR(__xludf.DUMMYFUNCTION("""COMPUTED_VALUE"""),"https://www.tiktok.com/@promos4m?lang=pt-BR") -> https://www.tiktok.com/@promos4m?lang=pt-BR | F21: =IFERROR(__xludf.DUMMYFUNCTION("""COMPUTED_VALUE"""),2367) -> 2367
A22: =IFERROR(__xludf.DUMMYFUNCTION("""COMPUTED_VALUE"""),322502351) -> 322502351 | B22: =IFERROR(__xludf.DUMMYFUNCTION("""COMPUTED_VALUE"""),"desconto") -> desconto | C22: =IFERROR(__xludf.DUMMYFUNCTION("""COMPUTED_VALUE"""),"https://www.instagram.com/santostecpromo/") -> https://www.instagram.com/santostecpromo/ | D22: =IFERROR(__xludf.DUMMYFUNCTION("""COMPUTED_VALUE"""),700) -> 700 | E22: =IFERROR(__xludf.DUMMYFUNCTION("""COMPUTED_VALUE"""),"https://www.tiktok.com/@santostecpromo") -> https://www.tiktok.com/@santostecpromo | F22: =IFERROR(__xludf.DUMMYFUNCTION("""COMPUTED_VALUE"""),5500) -> 5500
A23: =IFERROR(__xludf.DUMMYFUNCTION("""COMPUTED_VALUE"""),1375138586) -> 1375138586 | B23: =IFERROR(__xludf.DUMMYFUNCTION("""COMPUTED_VALUE"""),"Canaljptech") -> Canaljptech | C23: =IFERROR(__xludf.DUMMYFUNCTION("""COMPUTED_VALUE"""),"https://www.instagram.com/jptechgames/") -> https://www.instagram.com/jptechgames/ | D23: =IFERROR(__xludf.DUMMYFUNCTION("""COMPUTED_VALUE"""),28077) -> 28077 | E23: =IFERROR(__xludf.DUMMYFUNCTION("""COMPUTED_VALUE"""),"https://www.tiktok.com/@jptechgames_") -> https://www.tiktok.com/@jptechgames_ | F23: =IFERROR(__xludf.DUMMYFUNCTION("""COMPUTED_VALUE"""),172000) -> 172000
A24: =IFERROR(__xludf.DUMMYFUNCTION("""COMPUTED_VALUE"""),1366151811) -> 1366151811 | B24: =IFERROR(__xludf.DUMMYFUNCTION("""COMPUTED_VALUE"""),"pcdofafa") -> pcdofafa | C24: =IFERROR(__xludf.DUMMYFUNCTION("""COMPUTED_VALUE"""),"https://www.instagram.com/pcdofafa?igsh=MW15cTUyaDV2a3QwaQ==") -> https://www.instagram.com/pcdofafa?igsh=MW15cTUyaDV2a3QwaQ== | D24: =IFERROR(__xludf.DUMMYFUNCTION("""COMPUTED_VALUE"""),17000) -> 17000 | E24: =IFERROR(__xludf.DUMMYFUNCTION("""COMPUTED_VALUE"""),"https://www.tiktok.com/@pcdofafa?_t=ZM-8yzfN0wUGqz&_r=1") -> https://www.tiktok.com/@pcdofafa?_t=ZM-8yzfN0wUGqz&_r=1 | F24: =IFERROR(__xludf.DUMMYFUNCTION("""COMPUTED_VALUE"""),19000) -> 19000
A25: =IFERROR(__xludf.DUMMYFUNCTION("""COMPUTED_VALUE"""),1473563772) -> 1473563772 | B25: =IFERROR(__xludf.DUMMYFUNCTION("""COMPUTED_VALUE"""),"urubupromo") -> urubupromo | C25: =IFERROR(__xludf.DUMMYFUNCTION("""COMPUTED_VALUE"""),"instagram.com/urubupromo") -> instagram.com/urubupromo | D25: =IFERROR(__xludf.DUMMYFUNCTION("""COMPUTED_VALUE"""),63000) -> 63000
A26: =IFERROR(__xludf.DUMMYFUNCTION("""COMPUTED_VALUE"""),1249172900) -> 1249172900 | B26: =IFERROR(__xludf.DUMMYFUNCTION("""COMPUTED_VALUE"""),"tttech") -> tttech | C26: =IFERROR(__xludf.DUMMYFUNCTION("""COMPUTED_VALUE"""),"https://www.instagram.com/thalissontttech/") -> https://www.instagram.com/thalissontttech/ | D26: =IFERROR(__xludf.DUMMYFUNCTION("""COMPUTED_VALUE"""),20000) -> 20000 | E26: =IFERROR(__xludf.DUMMYFUNCTION("""COMPUTED_VALUE"""),"https://www.tiktok.com/@thalisson_tttech") -> https://www.tiktok.com/@thalisson_tttech | F26: =IFERROR(__xludf.DUMMYFUNCTION("""COMPUTED_VALUE"""),3000) -> 3000
A27: =IFERROR(__xludf.DUMMYFUNCTION("""COMPUTED_VALUE"""),1478114661) -> 1478114661 | B27: =IFERROR(__xludf.DUMMYFUNCTION("""COMPUTED_VALUE"""),"peguepromo") -> peguepromo | C27: =IFERROR(__xludf.DUMMYFUNCTION("""COMPUTED_VALUE"""),"https://www.instagram.com/peguepromo/") -> https://www.instagram.com/peguepromo/ | D27: =IFERROR(__xludf.DUMMYFUNCTION("""COMPUTED_VALUE"""),135000) -> 135000
A28: =IFERROR(__xludf.DUMMYFUNCTION("""COMPUTED_VALUE"""),1231576803) -> 1231576803 | B28: =IFERROR(__xludf.DUMMYFUNCTION("""COMPUTED_VALUE"""),"inovaleo") -> inovaleo | C28: =IFERROR(__xludf.DUMMYFUNCTION("""COMPUTED_VALUE"""),"https://www.instagram.com/inovaleo/?hl=pt-br") -> https://www.instagram.com/inovaleo/?hl=pt-br | D28: =IFERROR(__xludf.DUMMYFUNCTION("""COMPUTED_VALUE"""),492000) -> 492000 | E28: =IFERROR(__xludf.DUMMYFUNCTION("""COMPUTED_VALUE"""),"https://www.tiktok.com/@inovaleo?_t=8ce33tztExC&_r=1") -> https://www.tiktok.com/@inovaleo?_t=8ce33tztExC&_r=1 | F28: =IFERROR(__xludf.DUMMYFUNCTION("""COMPUTED_VALUE"""),134000) -> 134000
A29: =IFERROR(__xludf.DUMMYFUNCTION("""COMPUTED_VALUE"""),1450808630) -> 1450808630 | B29: =IFERROR(__xludf.DUMMYFUNCTION("""COMPUTED_VALUE"""),"agenciarice") -> agenciarice | C29: =IFERROR(__xludf.DUMMYFUNCTION("""COMPUTED_VALUE"""),"https://www.instagram.com/lobaopromo?igsh=MWRsZWlyNWI4bmU1aA==") -> https://www.instagram.com/lobaopromo?igsh=MWRsZWlyNWI4bmU1aA== | D29: =IFERROR(__xludf.DUMMYFUNCTION("""COMPUTED_VALUE"""),12000) -> 12000 | E29: =IFERROR(__xludf.DUMMYFUNCTION("""COMPUTED_VALUE"""),"https://x.com/lobaopromo?s=21") -> https://x.com/lobaopromo?s=21 | F29: =IFERROR(__xludf.DUMMYFUNCTION("""COMPUTED_VALUE"""),224000) -> 224000
A30: =IFERROR(__xludf.DUMMYFUNCTION("""COMPUTED_VALUE"""),1251879558) -> 1251879558 | B30: =IFERROR(__xludf.DUMMYFUNCTION("""COMPUTED_VALUE"""),"qualnotebook") -> qualnotebook | C30: =IFERROR(__xludf.DUMMYFUNCTION("""COMPUTED_VALUE"""),"https://www.instagram.com/qualnotebook/") -> https://www.instagram.com/qualnotebook/ | D30: =IFERROR(__xludf.DUMMYFUNCTION("""COMPUTED_VALUE"""),57000) -> 57000 | E30: =IFERROR(__xludf.DUMMYFUNCTION("""COMPUTED_VALUE"""),"https://www.tiktok.com/@qualnotebook/") -> https://www.tiktok.com/@qualnotebook/ | F30: =IFERROR(__xludf.DUMMYFUNCTION("""COMPUTED_VALUE"""),14000) -> 14000
A31: =IFERROR(__xludf.DUMMYFUNCTION("""COMPUTED_VALUE"""),2345017244) -> 2345017244 | B31: =IFERROR(__xludf.DUMMYFUNCTION("""COMPUTED_VALUE"""),"promosinc") -> promosinc | C31: =IFERROR(__xludf.DUMMYFUNCTION("""COMPUTED_VALUE"""),"https://www.instagram.com/pegar.promo") -> https://www.instagram.com/pegar.promo | D31: =IFERROR(__xludf.DUMMYFUNCTION("""COMPUTED_VALUE"""),140) -> 140
A32: =IFERROR(__xludf.DUMMYFUNCTION("""COMPUTED_VALUE"""),1453452471) -> 1453452471 | B32: =IFERROR(__xludf.DUMMYFUNCTION("""COMPUTED_VALUE"""),"Daniel Reenlsober") -> Daniel Reenlsober | C32: =IFERROR(__xludf.DUMMYFUNCTION("""COMPUTED_VALUE"""),"https://www.instagram.com/danielreen_") -> https://www.instagram.com/danielreen_ | D32: =IFERROR(__xludf.DUMMYFUNCTION("""COMPUTED_VALUE"""),10800) -> 10800 | E32: =IFERROR(__xludf.DUMMYFUNCTION("""COMPUTED_VALUE"""),"https://www.tiktok.com/@danielreen_") -> https://www.tiktok.com/@danielreen_ | F32: =IFERROR(__xludf.DUMMYFUNCTION("""COMPUTED_VALUE"""),2300) -> 2300
A33: =IFERROR(__xludf.DUMMYFUNCTION("""COMPUTED_VALUE"""),1161200505) -> 1161200505 | B33: =IFERROR(__xludf.DUMMYFUNCTION("""COMPUTED_VALUE"""),"mastertechjr") -> mastertechjr | C33: =IFERROR(__xludf.DUMMYFUNCTION("""COMPUTED_VALUE"""),"www.instagran.com/mastertechjr") -> www.instagran.com/mastertechjr | D33: =IFERROR(__xludf.DUMMYFUNCTION("""COMPUTED_VALUE"""),3019) -> 3019
A34: =IFERROR(__xludf.DUMMYFUNCTION("""COMPUTED_VALUE"""),1374758175) -> 1374758175 | B34: =IFERROR(__xludf.DUMMYFUNCTION("""COMPUTED_VALUE"""),"promotop") -> promotop | C34: =IFERROR(__xludf.DUMMYFUNCTION("""COMPUTED_VALUE"""),"https://www.instagram.com/promotopoficial/?hl=pt-br") -> https://www.instagram.com/promotopoficial/?hl=pt-br | D34: =IFERROR(__xludf.DUMMYFUNCTION("""COMPUTED_VALUE"""),31000) -> 31000 | E34: =IFERROR(__xludf.DUMMYFUNCTION("""COMPUTED_VALUE"""),"https://www.tiktok.com/@canalpromotop") -> https://www.tiktok.com/@canalpromotop | F34: =IFERROR(__xludf.DUMMYFUNCTION("""COMPUTED_VALUE"""),2300) -> 2300
A35: =IFERROR(__xludf.DUMMYFUNCTION("""COMPUTED_VALUE"""),268850426) -> 268850426 | B35: =IFERROR(__xludf.DUMMYFUNCTION("""COMPUTED_VALUE"""),"jeffrecomenda") -> jeffrecomenda | C35: =IFERROR(__xludf.DUMMYFUNCTION("""COMPUTED_VALUE"""),"https://www.instagram.com/jeffrecomenda?igsh=czA1bWVubm16M205") -> https://www.instagram.com/jeffrecomenda?igsh=czA1bWVubm16M205 | D35: =IFERROR(__xludf.DUMMYFUNCTION("""COMPUTED_VALUE"""),38000) -> 38000 | E35: =IFERROR(__xludf.DUMMYFUNCTION("""COMPUTED_VALUE"""),"https://www.tiktok.com/@jeffrecomenda?_t=ZM-8yqmv34HBgM&_r=1") -> https://www.tiktok.com/@jeffrecomenda?_t=ZM-8yqmv34HBgM&_r=1 | F35: =IFERROR(__xludf.DUMMYFUNCTION("""COMPUTED_VALUE"""),27000) -> 27000
A36: =IFERROR(__xludf.DUMMYFUNCTION("""COMPUTED_VALUE"""),1426808500) -> 1426808500 | B36: =IFERROR(__xludf.DUMMYFUNCTION("""COMPUTED_VALUE"""),"promoimperdivel") -> promoimperdivel | C36: =IFERROR(__xludf.DUMMYFUNCTION("""COMPUTED_VALUE"""),"instagram.com/promoimperdivel_") -> instagram.com/promoimperdivel_ | D36: =IFERROR(__xludf.DUMMYFUNCTION("""COMPUTED_VALUE"""),8000) -> 8000
A37: =IFERROR(__xludf.DUMMYFUNCTION("""COMPUTED_VALUE"""),1114585317) -> 1114585317 | B37: =IFERROR(__xludf.DUMMYFUNCTION("""COMPUTED_VALUE"""),"bench promos") -> bench promos | C37: =IFERROR(__xludf.DUMMYFUNCTION("""COMPUTED_VALUE"""),"https://www.instagram.com/lucas.ishii/") -> https://www.instagram.com/lucas.ishii/ | D37: =IFERROR(__xludf.DUMMYFUNCTION("""COMPUTED_VALUE"""),53200) -> 53200 | E37: =IFERROR(__xludf.DUMMYFUNCTION("""COMPUTED_VALUE"""),"https://www.tiktok.com/@lucas_ishii?lang=pt-BR") -> https://www.tiktok.com/@lucas_ishii?lang=pt-BR | F37: =IFERROR(__xludf.DUMMYFUNCTION("""COMPUTED_VALUE"""),111700) -> 111700
A38: =IFERROR(__xludf.DUMMYFUNCTION("""COMPUTED_VALUE"""),1370750164) -> 1370750164 | B38: =IFERROR(__xludf.DUMMYFUNCTION("""COMPUTED_VALUE"""),"switchxz") -> switchxz | C38: =IFERROR(__xludf.DUMMYFUNCTION("""COMPUTED_VALUE"""),"https://www.instagram.com/linksbrazil (não utilizo)") -> https://www.instagram.com/linksbrazil (não utilizo) | D38: =IFERROR(__xludf.DUMMYFUNCTION("""COMPUTED_VALUE"""),158) -> 158
A39: =IFERROR(__xludf.DUMMYFUNCTION("""COMPUTED_VALUE"""),251645009) -> 251645009 | B39: =IFERROR(__xludf.DUMMYFUNCTION("""COMPUTED_VALUE"""),"novosprodutos") -> novosprodutos | C39: =IFERROR(__xludf.DUMMYFUNCTION("""COMPUTED_VALUE"""),"https://www.instagram.com/novosprodutos") -> https://www.instagram.com/novosprodutos | D39: =IFERROR(__xludf.DUMMYFUNCTION("""COMPUTED_VALUE"""),4000000) -> 4000000
A40: =IFERROR(__xludf.DUMMYFUNCTION("""COMPUTED_VALUE"""),263391604) -> 263391604 | B40: =IFERROR(__xludf.DUMMYFUNCTION("""COMPUTED_VALUE"""),"so_promocoesdodia") -> so_promocoesdodia | C40: =IFERROR(__xludf.DUMMYFUNCTION("""COMPUTED_VALUE"""),"https://www.instagram.com/so_promocoesdodia?igsh=MTBieDVweDN3eXN5eg==") -> https://www.instagram.com/so_promocoesdodia?igsh=MTBieDVweDN3eXN5eg== | D40: =IFERROR(__xludf.DUMMYFUNCTION("""COMPUTED_VALUE"""),950000) -> 950000
A41: =IFERROR(__xludf.DUMMYFUNCTION("""COMPUTED_VALUE"""),1469910364) -> 1469910364 | B41: =IFERROR(__xludf.DUMMYFUNCTION("""COMPUTED_VALUE"""),"clubedopresidente") -> clubedopresidente | C41: =IFERROR(__xludf.DUMMYFUNCTION("""COMPUTED_VALUE"""),"https://www.instagram.com/clubedopresidente/") -> https://www.instagram.com/clubedopresidente/ | D41: =IFERROR(__xludf.DUMMYFUNCTION("""COMPUTED_VALUE"""),161000) -> 161000 | E41: =IFERROR(__xludf.DUMMYFUNCTION("""COMPUTED_VALUE"""),"https://www.tiktok.com/@clubedopresidente?_t=ZM-8xfxfiIojpd&_r=1") -> https://www.tiktok.com/@clubedopresidente?_t=ZM-8xfxfiIojpd&_r=1 | F41: =IFERROR(__xludf.DUMMYFUNCTION("""COMPUTED_VALUE"""),206) -> 206
A42: =IFERROR(__xludf.DUMMYFUNCTION("""COMPUTED_VALUE"""),199199140) -> 199199140 | B42: =IFERROR(__xludf.DUMMYFUNCTION("""COMPUTED_VALUE"""),"techbr") -> techbr | C42: =IFERROR(__xludf.DUMMYFUNCTION("""COMPUTED_VALUE"""),"https://www.instagram.com/canaltechbr/profilecard/?igsh=OG1uOTEwa2s5NWd3") -> https://www.instagram.com/canaltechbr/profilecard/?igsh=OG1uOTEwa2s5NWd3 | D42: =IFERROR(__xludf.DUMMYFUNCTION("""COMPUTED_VALUE"""),7800) -> 7800 | E42: =IFERROR(__xludf.DUMMYFUNCTION("""COMPUTED_VALUE"""),"https://www.tiktok.com/@techbrcanal?_t=ZM-8yW6ZmJSSVs&_r=1") -> https://www.tiktok.com/@techbrcanal?_t=ZM-8yW6ZmJSSVs&_r=1 | F42: =IFERROR(__xludf.DUMMYFUNCTION("""COMPUTED_VALUE"""),19800) -> 19800
A43: =IFERROR(__xludf.DUMMYFUNCTION("""COMPUTED_VALUE"""),1461583629) -> 1461583629 | B43: =IFERROR(__xludf.DUMMYFUNCTION("""COMPUTED_VALUE"""),"tempromo") -> tempromo | C43: =IFERROR(__xludf.DUMMYFUNCTION("""COMPUTED_VALUE"""),"https://www.instagram.com/tem_promo") -> https://www.instagram.com/tem_promo | D43: =IFERROR(__xludf.DUMMYFUNCTION("""COMPUTED_VALUE"""),588000) -> 588000 | E43: =IFERROR(__xludf.DUMMYFUNCTION("""COMPUTED_VALUE"""),"https://www.tiktok.com/@tem.promo") -> https://www.tiktok.com/@tem.promo | F43: =IFERROR(__xludf.DUMMYFUNCTION("""COMPUTED_VALUE"""),188000) -> 188000
A44: =IFERROR(__xludf.DUMMYFUNCTION("""COMPUTED_VALUE"""),1159690723) -> 1159690723 | B44: =IFERROR(__xludf.DUMMYFUNCTION("""COMPUTED_VALUE"""),"techmelhores") -> techmelhores | C44: =IFERROR(__xludf.DUMMYFUNCTION("""COMPUTED_VALUE"""),"") | D44: =IFERROR(__xludf.DUMMYFUNCTION("""COMPUTED_VALUE"""),"") | E44: =IFERROR(__xludf.DUMMYFUNCTION("""COMPUTED_VALUE"""),"") | F44: =IFERROR(__xludf.DUMMYFUNCTION("""COMPUTED_VALUE"""),"")
A45: =IFERROR(__xludf.DUMMYFUNCTION("""COMPUTED_VALUE"""),1387667693) -> 1387667693 | B45: =IFERROR(__xludf.DUMMYFUNCTION("""COMPUTED_VALUE"""),"descontoemgames") -> descontoemgames | C45: =IFERROR(__xludf.DUMMYFUNCTION("""COMPUTED_VALUE"""),"https://www.instagram.com/descontoemgames") -> https://www.instagram.com/descontoemgames | D45: =IFERROR(__xludf.DUMMYFUNCTION("""COMPUTED_VALUE"""),23800) -> 23800 | E45: =IFERROR(__xludf.DUMMYFUNCTION("""COMPUTED_VALUE"""),"https://www.tiktok.com/@republicadg") -> https://www.tiktok.com/@republicadg | F45: =IFERROR(__xludf.DUMMYFUNCTION("""COMPUTED_VALUE"""),1012) -> 1012
A46: =IFERROR(__xludf.DUMMYFUNCTION("""COMPUTED_VALUE"""),2389628095) -> 2389628095 | B46: =IFERROR(__xludf.DUMMYFUNCTION("""COMPUTED_VALUE"""),"ofcprominho") -> ofcprominho | C46: =IFERROR(__xludf.DUMMYFUNCTION("""COMPUTED_VALUE"""),"https://x.com/ofcpromo") -> https://x.com/ofcpromo | D46: =IFERROR(__xludf.DUMMYFUNCTION("""COMPUTED_VALUE"""),381000) -> 381000 | E46: =IFERROR(__xludf.DUMMYFUNCTION("""COMPUTED_VALUE"""),"https://x.com/ofctenis") -> https://x.com/ofctenis | F46: =IFERROR(__xludf.DUMMYFUNCTION("""COMPUTED_VALUE"""),95000) -> 95000
A47: =IFERROR(__xludf.DUMMYFUNCTION("""COMPUTED_VALUE"""),1424070748) -> 1424070748 | B47: =IFERROR(__xludf.DUMMYFUNCTION("""COMPUTED_VALUE"""),"lapromotion") -> lapromotion | C47: =IFERROR(__xludf.DUMMYFUNCTION("""COMPUTED_VALUE"""),"https://instagram.com/lapromotion_") -> https://instagram.com/lapromotion_ | D47: =IFERROR(__xludf.DUMMYFUNCTION("""COMPUTED_VALUE"""),42000) -> 42000
A48: =IFERROR(__xludf.DUMMYFUNCTION("""COMPUTED_VALUE"""),15665498) -> 15665498 | B48: =IFERROR(__xludf.DUMMYFUNCTION("""COMPUTED_VALUE"""),"kotas") -> kotas | C48: =IFERROR(__xludf.DUMMYFUNCTION("""COMPUTED_VALUE"""),"https://www.instagram.com/clube.kotas/") -> https://www.instagram.com/clube.kotas/ | D48: =IFERROR(__xludf.DUMMYFUNCTION("""COMPUTED_VALUE"""),2000) -> 2000 | E48: =IFERROR(__xludf.DUMMYFUNCTION("""COMPUTED_VALUE"""),"https://www.tiktok.com/@clube.kotas") -> https://www.tiktok.com/@clube.kotas | F48: =IFERROR(__xludf.DUMMYFUNCTION("""COMPUTED_VALUE"""),5000) -> 5000
A49: =IFERROR(__xludf.DUMMYFUNCTION("""COMPUTED_VALUE"""),521028663) -> 521028663 | B49: =IFERROR(__xludf.DUMMYFUNCTION("""COMPUTED_VALUE"""),"promotecgames") -> promotecgames | C49: =IFERROR(__xludf.DUMMYFUNCTION("""COMPUTED_VALUE"""),"https://www.instagram.com/promotecgames/ e https://www.instagram.com/promotecdescontos/") -> https://www.instagram.com/promotecgames/ e https://www.instagram.com/promotecdescontos/ | D49: =IFERROR(__xludf.DUMMYFUNCTION("""COMPUTED_VALUE"""),22000) -> 22000 | E49: =IFERROR(__xludf.DUMMYFUNCTION("""COMPUTED_VALUE"""),"https://www.tiktok.com/@promotecgames") -> https://www.tiktok.com/@promotecgames | F49: =IFERROR(__xludf.DUMMYFUNCTION("""COMPUTED_VALUE"""),1590) -> 1590
A50: =IFERROR(__xludf.DUMMYFUNCTION("""COMPUTED_VALUE"""),150242200) -> 150242200 | B50: =IFERROR(__xludf.DUMMYFUNCTION("""COMPUTED_VALUE"""),"preguicaofertas") -> preguicaofertas | C50: =IFERROR(__xludf.DUMMYFUNCTION("""COMPUTED_VALUE"""),"https://www.instagram.com/preguicaofertas/") -> https://www.instagram.com/preguicaofertas/ | D50: =IFERROR(__xludf.DUMMYFUNCTION("""COMPUTED_VALUE"""),3500) -> 3500 | E50: =IFERROR(__xludf.DUMMYFUNCTION("""COMPUTED_VALUE"""),"https://x.com/preguicaofertas") -> https://x.com/preguicaofertas | F50: =IFERROR(__xludf.DUMMYFUNCTION("""COMPUTED_VALUE"""),61800) -> 61800
A51: =IFERROR(__xludf.DUMMYFUNCTION("""COMPUTED_VALUE"""),1446287023) -> 1446287023 | B51: =IFERROR(__xludf.DUMMYFUNCTION("""COMPUTED_VALUE"""),"garimpeiofertas") -> garimpeiofertas | C51: =IFERROR(__xludf.DUMMYFUNCTION("""COMPUTED_VALUE"""),"https://www.instagram.com/garimpei.ofertas/") -> https://www.instagram.com/garimpei.ofertas/ | D51: =IFERROR(__xludf.DUMMYFUNCTION("""COMPUTED_VALUE"""),180000) -> 180000 | E51: =IFERROR(__xludf.DUMMYFUNCTION("""COMPUTED_VALUE"""),"https://www.tiktok.com/@garimpeiofertasoficial?_t=ZM-8xgGGnDzwt3&_r=") -> https://www.tiktok.com/@garimpeiofertasoficial?_t=ZM-8xgGGnDzwt3&_r= | F51: =IFERROR(__xludf.DUMMYFUNCTION("""COMPUTED_VALUE"""),670) -> 670
A52: =IFERROR(__xludf.DUMMYFUNCTION("""COMPUTED_VALUE"""),268300847) -> 268300847 | B52: =IFERROR(__xludf.DUMMYFUNCTION("""COMPUTED_VALUE"""),"matheuskise") -> matheuskise | C52: =IFERROR(__xludf.DUMMYFUNCTION("""COMPUTED_VALUE"""),"http://instagram.com/matheuskise/") -> http://instagram.com/matheuskise/ | D52: =IFERROR(__xludf.DUMMYFUNCTION("""COMPUTED_VALUE"""),110000) -> 110000
A53: =IFERROR(__xludf.DUMMYFUNCTION("""COMPUTED_VALUE"""),1427325193) -> 1427325193 | B53: =IFERROR(__xludf.DUMMYFUNCTION("""COMPUTED_VALUE"""),"tabaratasso") -> tabaratasso | C53: =IFERROR(__xludf.DUMMYFUNCTION("""COMPUTED_VALUE"""),"https://www.instagram.com/tabaratasso?igsh=MWdmYWhhcnphZmZ5bg%3D%3D&utm_source=qr") -> https://www.instagram.com/tabaratasso?igsh=MWdmYWhhcnphZmZ5bg%3D%3D&utm_source=qr | D53: =IFERROR(__xludf.DUMMYFUNCTION("""COMPUTED_VALUE"""),97000) -> 97000 | E53: =IFERROR(__xludf.DUMMYFUNCTION("""COMPUTED_VALUE"""),"https://www.tiktok.com/@tabaratasso?_t=ZM-8xhtvV1QOAQ&_r=1") -> https://www.tiktok.com/@tabaratasso?_t=ZM-8xhtvV1QOAQ&_r=1 | F53: =IFERROR(__xludf.DUMMYFUNCTION("""COMPUTED_VALUE"""),107712) -> 107712
A54: =IFERROR(__xludf.DUMMYFUNCTION("""COMPUTED_VALUE"""),798617488) -> 798617488 | B54: =IFERROR(__xludf.DUMMYFUNCTION("""COMPUTED_VALUE"""),"Fraguas84") -> Fraguas84 | C54: =IFERROR(__xludf.DUMMYFUNCTION("""COMPUTED_VALUE"""),"https://www.instagram.com/fraguas84/") -> https://www.instagram.com/fraguas84/ | D54: =IFERROR(__xludf.DUMMYFUNCTION("""COMPUTED_VALUE"""),67000) -> 67000
A55: =IFERROR(__xludf.DUMMYFUNCTION("""COMPUTED_VALUE"""),1342941619) -> 1342941619 | B55: =IFERROR(__xludf.DUMMYFUNCTION("""COMPUTED_VALUE"""),"tecvariedades") -> tecvariedades | C55: =IFERROR(__xludf.DUMMYFUNCTION("""COMPUTED_VALUE"""),"https://www.instagram.com/tech_variedadesoficial") -> https://www.instagram.com/tech_variedadesoficial | D55: =IFERROR(__xludf.DUMMYFUNCTION("""COMPUTED_VALUE"""),23000) -> 23000 | E55: =IFERROR(__xludf.DUMMYFUNCTION("""COMPUTED_VALUE"""),"https://www.tiktok.com/@tech_variedadesoficial") -> https://www.tiktok.com/@tech_variedadesoficial | F55: =IFERROR(__xludf.DUMMYFUNCTION("""COMPUTED_VALUE"""),61000) -> 61000
A56: =IFERROR(__xludf.DUMMYFUNCTION("""COMPUTED_VALUE"""),678610452) -> 678610452 | B56: =IFERROR(__xludf.DUMMYFUNCTION("""COMPUTED_VALUE"""),"samuelf3lipe") -> samuelf3lipe | C56: =IFERROR(__xludf.DUMMYFUNCTION("""COMPUTED_VALUE"""),"https://www.instagram.com/samuelf3lipe") -> https://www.instagram.com/samuelf3lipe | D56: =IFERROR(__xludf.DUMMYFUNCTION("""COMPUTED_VALUE"""),5) -> 5 | E56: =IFERROR(__xludf.DUMMYFUNCTION("""COMPUTED_VALUE"""),"https://www.tiktok.com/@samuelf3lipe_") -> https://www.tiktok.com/@samuelf3lipe_ | F56: =IFERROR(__xludf.DUMMYFUNCTION("""COMPUTED_VALUE"""),56000) -> 56000
A57: =IFERROR(__xludf.DUMMYFUNCTION("""COMPUTED_VALUE"""),2457362902) -> 2457362902 | B57: =IFERROR(__xludf.DUMMYFUNCTION("""COMPUTED_VALUE"""),"promosdebrother") -> promosdebrother | C57: =IFERROR(__xludf.DUMMYFUNCTION("""COMPUTED_VALUE"""),"") | D57: =IFERROR(__xludf.DUMMYFUNCTION("""COMPUTED_VALUE"""),"") | E57: =IFERROR(__xludf.DUMMYFUNCTION("""COMPUTED_VALUE"""),"") | F57: =IFERROR(__xludf.DUMMYFUNCTION("""COMPUTED_VALUE"""),"")
A58: =IFERROR(__xludf.DUMMYFUNCTION("""COMPUTED_VALUE"""),44352982) -> 44352982 | B58: =IFERROR(__xludf.DUMMYFUNCTION("""COMPUTED_VALUE"""),"tjgaming") -> tjgaming | C58: =IFERROR(__xludf.DUMMYFUNCTION("""COMPUTED_VALUE"""),"https://www.instagram.com/tjgamingbr") -> https://www.instagram.com/tjgamingbr | D58: =IFERROR(__xludf.DUMMYFUNCTION("""COMPUTED_VALUE"""),133000) -> 133000 | E58: =IFERROR(__xludf.DUMMYFUNCTION("""COMPUTED_VALUE"""),"https://www.tiktok.com/@tjgamingbr_?_t=ZM-8z4IhQdgP4A&_r=1") -> https://www.tiktok.com/@tjgamingbr_?_t=ZM-8z4IhQdgP4A&_r=1 | F58: =IFERROR(__xludf.DUMMYFUNCTION("""COMPUTED_VALUE"""),433400) -> 433400
A59: =IFERROR(__xludf.DUMMYFUNCTION("""COMPUTED_VALUE"""),330532268) -> 330532268 | B59: =IFERROR(__xludf.DUMMYFUNCTION("""COMPUTED_VALUE"""),"achadosempromo") -> achadosempromo | C59: =IFERROR(__xludf.DUMMYFUNCTION("""COMPUTED_VALUE"""),"https://www.instagram.com/achados.em.promo") -> https://www.instagram.com/achados.em.promo | D59: =IFERROR(__xludf.DUMMYFUNCTION("""COMPUTED_VALUE"""),540000) -> 540000
A60: =IFERROR(__xludf.DUMMYFUNCTION("""COMPUTED_VALUE"""),1399249654) -> 1399249654 | B60: =IFERROR(__xludf.DUMMYFUNCTION("""COMPUTED_VALUE"""),"garimpeiros") -> garimpeiros | C60: =IFERROR(__xludf.DUMMYFUNCTION("""COMPUTED_VALUE"""),"https://instagram.com/garimpeirosoficial") -> https://instagram.com/garimpeirosoficial | D60: =IFERROR(__xludf.DUMMYFUNCTION("""COMPUTED_VALUE"""),254000) -> 254000
A61: =IFERROR(__xludf.DUMMYFUNCTION("""COMPUTED_VALUE"""),149518102) -> 149518102 | B61: =IFERROR(__xludf.DUMMYFUNCTION("""COMPUTED_VALUE"""),"bizudaspromocoes") -> bizudaspromocoes | C61: =IFERROR(__xludf.DUMMYFUNCTION("""COMPUTED_VALUE"""),"https://www.instagram.com/bizudaspromocoes/") -> https://www.instagram.com/bizudaspromocoes/ | D61: =IFERROR(__xludf.DUMMYFUNCTION("""COMPUTED_VALUE"""),358000) -> 358000
A62: =IFERROR(__xludf.DUMMYFUNCTION("""COMPUTED_VALUE"""),1156310262) -> 1156310262 | B62: =IFERROR(__xludf.DUMMYFUNCTION("""COMPUTED_VALUE"""),"sddescontos") -> sddescontos | C62: =IFERROR(__xludf.DUMMYFUNCTION("""COMPUTED_VALUE"""),"https://www.instagram.com/sddescontos?igsh=ZnRycXduNWl4c2Fp") -> https://www.instagram.com/sddescontos?igsh=ZnRycXduNWl4c2Fp | D62: =IFERROR(__xludf.DUMMYFUNCTION("""COMPUTED_VALUE"""),6000) -> 6000 | E62: =IFERROR(__xludf.DUMMYFUNCTION("""COMPUTED_VALUE"""),"https://www.tiktok.com/@sddescontos?_t=ZM-8xhjbOzsii0&_r=1") -> https://www.tiktok.com/@sddescontos?_t=ZM-8xhjbOzsii0&_r=1 | F62: =IFERROR(__xludf.DUMMYFUNCTION("""COMPUTED_VALUE"""),200) -> 200
A63: =IFERROR(__xludf.DUMMYFUNCTION("""COMPUTED_VALUE"""),1365511504) -> 1365511504 | B63: =IFERROR(__xludf.DUMMYFUNCTION("""COMPUTED_VALUE"""),"geekloko") -> geekloko | C63: =IFERROR(__xludf.DUMMYFUNCTION("""COMPUTED_VALUE"""),"https://www.instagram.com/geek.loko") -> https://www.instagram.com/geek.loko | D63: =IFERROR(__xludf.DUMMYFUNCTION("""COMPUTED_VALUE"""),64000) -> 64000 | E63: =IFERROR(__xludf.DUMMYFUNCTION("""COMPUTED_VALUE"""),"https://www.tiktok.com/@geek.loko") -> https://www.tiktok.com/@geek.loko | F63: =IFERROR(__xludf.DUMMYFUNCTION("""COMPUTED_VALUE"""),8100) -> 8100
A64: =IFERROR(__xludf.DUMMYFUNCTION("""COMPUTED_VALUE"""),1420365380) -> 1420365380 | B64: =IFERROR(__xludf.DUMMYFUNCTION("""COMPUTED_VALUE"""),"pincei") -> pincei | C64: =IFERROR(__xludf.DUMMYFUNCTION("""COMPUTED_VALUE"""),"https://www.instagram.com/pinceiofertas?igsh=MTNtemlyYmF5a2dwcQ==") -> https://www.instagram.com/pinceiofertas?igsh=MTNtemlyYmF5a2dwcQ== | D64: =IFERROR(__xludf.DUMMYFUNCTION("""COMPUTED_VALUE"""),700000) -> 700000 | E64: =IFERROR(__xludf.DUMMYFUNCTION("""COMPUTED_VALUE"""),"https://www.tiktok.com/@pinceiofertas?_t=ZM-8ysPAlXUzzC&_r=1") -> https://www.tiktok.com/@pinceiofertas?_t=ZM-8ysPAlXUzzC&_r=1 | F64: =IFERROR(__xludf.DUMMYFUNCTION("""COMPUTED_VALUE"""),200000) -> 200000
A65: =IFERROR(__xludf.DUMMYFUNCTION("""COMPUTED_VALUE"""),1185718745) -> 1185718745 | B65: =IFERROR(__xludf.DUMMYFUNCTION("""COMPUTED_VALUE"""),"ofertasgamer") -> ofertasgamer | C65: =IFERROR(__xludf.DUMMYFUNCTION("""COMPUTED_VALUE"""),"https://www.instagram.com/ofertasgamer_oficial/") -> https://www.instagram.com/ofertasgamer_oficial/ | D65: =IFERROR(__xludf.DUMMYFUNCTION("""COMPUTED_VALUE"""),10200) -> 10200 | E65: =IFERROR(__xludf.DUMMYFUNCTION("""COMPUTED_VALUE"""),"https://www.tiktok.com/@ofertasgamer_oficial") -> https://www.tiktok.com/@ofertasgamer_oficial | F65: =IFERROR(__xludf.DUMMYFUNCTION("""COMPUTED_VALUE"""),3743) -> 3743
A66: =IFERROR(__xludf.DUMMYFUNCTION("""COMPUTED_VALUE"""),1434694534) -> 1434694534 | B66: =IFERROR(__xludf.DUMMYFUNCTION("""COMPUTED_VALUE"""),"jogobarato") -> jogobarato | C66: =IFERROR(__xludf.DUMMYFUNCTION("""COMPUTED_VALUE"""),"") | D66: =IFERROR(__xludf.DUMMYFUNCTION("""COMPUTED_VALUE"""),"") | E66: =IFERROR(__xludf.DUMMYFUNCTION("""COMPUTED_VALUE"""),"") | F66: =IFERROR(__xludf.DUMMYFUNCTION("""COMPUTED_VALUE"""),"")
A67: =IFERROR(__xludf.DUMMYFUNCTION("""COMPUTED_VALUE"""),1947955373) -> 1947955373 | B67: =IFERROR(__xludf.DUMMYFUNCTION("""COMPUTED_VALUE"""),"guerradealsfit") -> guerradealsfit | C67: =IFERROR(__xludf.DUMMYFUNCTION("""COMPUTED_VALUE"""),"https://www.instagram.com/guerradealsfit") -> https://www.instagram.com/guerradealsfit | D67: =IFERROR(__xludf.DUMMYFUNCTION("""COMPUTED_VALUE"""),40000) -> 40000
A68: =IFERROR(__xludf.DUMMYFUNCTION("""COMPUTED_VALUE"""),2569994453) -> 2569994453 | B68: =IFERROR(__xludf.DUMMYFUNCTION("""COMPUTED_VALUE"""),"OLHADAPROMOS") -> OLHADAPROMOS | C68: =IFERROR(__xludf.DUMMYFUNCTION("""COMPUTED_VALUE"""),"") | D68: =IFERROR(__xludf.DUMMYFUNCTION("""COMPUTED_VALUE"""),"") | E68: =IFERROR(__xludf.DUMMYFUNCTION("""COMPUTED_VALUE"""),"") | F68: =IFERROR(__xludf.DUMMYFUNCTION("""COMPUTED_VALUE"""),"")
A69: =IFERROR(__xludf.DUMMYFUNCTION("""COMPUTED_VALUE"""),1082097965) -> 1082097965 | B69: =IFERROR(__xludf.DUMMYFUNCTION("""COMPUTED_VALUE"""),"Promobyte") -> Promobyte | C69: =IFERROR(__xludf.DUMMYFUNCTION("""COMPUTED_VALUE"""),"https://www.instagram.com/promobyteoficial") -> https://www.instagram.com/promobyteoficial | D69: =IFERROR(__xludf.DUMMYFUNCTION("""COMPUTED_VALUE"""),11000) -> 11000
A70: =IFERROR(__xludf.DUMMYFUNCTION("""COMPUTED_VALUE"""),1365706499) -> 1365706499 | B70: =IFERROR(__xludf.DUMMYFUNCTION("""COMPUTED_VALUE"""),"peperaio") -> peperaio | C70: =IFERROR(__xludf.DUMMYFUNCTION("""COMPUTED_VALUE"""),"http://instagram.com/lucaspeperaio") -> http://instagram.com/lucaspeperaio | D70: =IFERROR(__xludf.DUMMYFUNCTION("""COMPUTED_VALUE"""),8954) -> 8954 | E70: =IFERROR(__xludf.DUMMYFUNCTION("""COMPUTED_VALUE"""),"https://www.youtube.com/@PeperaioHardware (esta é a minha rede principal)") -> https://www.youtube.com/@PeperaioHardware (esta é a minha rede principal) | F70: =IFERROR(__xludf.DUMMYFUNCTION("""COMPUTED_VALUE"""),332000) -> 332000
A71: =IFERROR(__xludf.DUMMYFUNCTION("""COMPUTED_VALUE"""),1369622787) -> 1369622787 | B71: =IFERROR(__xludf.DUMMYFUNCTION("""COMPUTED_VALUE"""),"uduluiz") -> uduluiz | C71: =IFERROR(__xludf.DUMMYFUNCTION("""COMPUTED_VALUE"""),"https://www.instagram.com/bugueycomprey/") -> https://www.instagram.com/bugueycomprey/ | D71: =IFERROR(__xludf.DUMMYFUNCTION("""COMPUTED_VALUE"""),1700) -> 1700 | E71: =IFERROR(__xludf.DUMMYFUNCTION("""COMPUTED_VALUE"""),"https://www.tiktok.com/@uduluiz") -> https://www.tiktok.com/@uduluiz | F71: =IFERROR(__xludf.DUMMYFUNCTION("""COMPUTED_VALUE"""),9600) -> 9600
A72: =IFERROR(__xludf.DUMMYFUNCTION("""COMPUTED_VALUE"""),1434918733) -> 1434918733 | B72: =IFERROR(__xludf.DUMMYFUNCTION("""COMPUTED_VALUE"""),"babypromokids") -> babypromokids | C72: =IFERROR(__xludf.DUMMYFUNCTION("""COMPUTED_VALUE"""),"https://www.instagram.com/babypromokids/") -> https://www.instagram.com/babypromokids/ | D72: =IFERROR(__xludf.DUMMYFUNCTION("""COMPUTED_VALUE"""),999000) -> 999000 | E72: =IFERROR(__xludf.DUMMYFUNCTION("""COMPUTED_VALUE"""),"https://www.tiktok.com/@babypromokids") -> https://www.tiktok.com/@babypromokids | F72: =IFERROR(__xludf.DUMMYFUNCTION("""COMPUTED_VALUE"""),98000) -> 98000
A73: =IFERROR(__xludf.DUMMYFUNCTION("""COMPUTED_VALUE"""),2046114897) -> 2046114897 | B73: =IFERROR(__xludf.DUMMYFUNCTION("""COMPUTED_VALUE"""),"fadadoscupons") -> fadadoscupons | C73: =IFERROR(__xludf.DUMMYFUNCTION("""COMPUTED_VALUE"""),"https://www.instagram.com/ninjaofertas_/") -> https://www.instagram.com/ninjaofertas_/ | D73: =IFERROR(__xludf.DUMMYFUNCTION("""COMPUTED_VALUE"""),7200) -> 7200
A74: =IFERROR(__xludf.DUMMYFUNCTION("""COMPUTED_VALUE"""),1451916544) -> 1451916544 | B74: =IFERROR(__xludf.DUMMYFUNCTION("""COMPUTED_VALUE"""),"tosemkit") -> tosemkit | C74: =IFERROR(__xludf.DUMMYFUNCTION("""COMPUTED_VALUE"""),"https://www.instagram.com/tosemkit/") -> https://www.instagram.com/tosemkit/ | D74: =IFERROR(__xludf.DUMMYFUNCTION("""COMPUTED_VALUE"""),240000) -> 240000 | E74: =IFERROR(__xludf.DUMMYFUNCTION("""COMPUTED_VALUE"""),"https://www.tiktok.com/@tosemkit") -> https://www.tiktok.com/@tosemkit | F74: =IFERROR(__xludf.DUMMYFUNCTION("""COMPUTED_VALUE"""),324000) -> 324000
A75: =IFERROR(__xludf.DUMMYFUNCTION("""COMPUTED_VALUE"""),1482183974) -> 1482183974 | B75: =IFERROR(__xludf.DUMMYFUNCTION("""COMPUTED_VALUE"""),"promohub") -> promohub | C75: =IFERROR(__xludf.DUMMYFUNCTION("""COMPUTED_VALUE"""),"https://www.instagram.com/promohub.br/") -> https://www.instagram.com/promohub.br/ | D75: =IFERROR(__xludf.DUMMYFUNCTION("""COMPUTED_VALUE"""),39700) -> 39700
A76: =IFERROR(__xludf.DUMMYFUNCTION("""COMPUTED_VALUE"""),2351879503) -> 2351879503 | B76: =IFERROR(__xludf.DUMMYFUNCTION("""COMPUTED_VALUE"""),"br20250326135135") -> br20250326135135 | C76: =IFERROR(__xludf.DUMMYFUNCTION("""COMPUTED_VALUE"""),"https://www.instagram.com/rodrigoapolloni/") -> https://www.instagram.com/rodrigoapolloni/ | D76: =IFERROR(__xludf.DUMMYFUNCTION("""COMPUTED_VALUE"""),256) -> 256
A77: =IFERROR(__xludf.DUMMYFUNCTION("""COMPUTED_VALUE"""),1514602500) -> 1514602500 | B77: =IFERROR(__xludf.DUMMYFUNCTION("""COMPUTED_VALUE"""),"recomendou") -> recomendou | C77: =IFERROR(__xludf.DUMMYFUNCTION("""COMPUTED_VALUE"""),"promodica.com.br") -> promodica.com.br | D77: =IFERROR(__xludf.DUMMYFUNCTION("""COMPUTED_VALUE"""),0) -> 0 | E77: =IFERROR(__xludf.DUMMYFUNCTION("""COMPUTED_VALUE"""),"promodica.com.br") -> promodica.com.br | F77: =IFERROR(__xludf.DUMMYFUNCTION("""COMPUTED_VALUE"""),0) -> 0
A78: =IFERROR(__xludf.DUMMYFUNCTION("""COMPUTED_VALUE"""),1321102962) -> 1321102962 | B78: =IFERROR(__xludf.DUMMYFUNCTION("""COMPUTED_VALUE"""),"eusoubarone") -> eusoubarone | C78: =IFERROR(__xludf.DUMMYFUNCTION("""COMPUTED_VALUE"""),"") | D78: =IFERROR(__xludf.DUMMYFUNCTION("""COMPUTED_VALUE"""),"") | E78: =IFERROR(__xludf.DUMMYFUNCTION("""COMPUTED_VALUE"""),"") | F78: =IFERROR(__xludf.DUMMYFUNCTION("""COMPUTED_VALUE"""),"")
A79: =IFERROR(__xludf.DUMMYFUNCTION("""COMPUTED_VALUE"""),495016443) -> 495016443 | B79: =IFERROR(__xludf.DUMMYFUNCTION("""COMPUTED_VALUE"""),"ofertasgeek") -> ofertasgeek | C79: =IFERROR(__xludf.DUMMYFUNCTION("""COMPUTED_VALUE"""),"https://www.instagram.com/_ofertasgeek/") -> https://www.instagram.com/_ofertasgeek/ | D79: =IFERROR(__xludf.DUMMYFUNCTION("""COMPUTED_VALUE"""),53000) -> 53000
A80: =IFERROR(__xludf.DUMMYFUNCTION("""COMPUTED_VALUE"""),1457441247) -> 1457441247 | B80: =IFERROR(__xludf.DUMMYFUNCTION("""COMPUTED_VALUE"""),"cupons") -> cupons | C80: =IFERROR(__xludf.DUMMYFUNCTION("""COMPUTED_VALUE"""),"https://www.instagram.com/reduzaoficial/") -> https://www.instagram.com/reduzaoficial/ | D80: =IFERROR(__xludf.DUMMYFUNCTION("""COMPUTED_VALUE"""),10000) -> 10000
A81: =IFERROR(__xludf.DUMMYFUNCTION("""COMPUTED_VALUE"""),200355621) -> 200355621 | B81: =IFERROR(__xludf.DUMMYFUNCTION("""COMPUTED_VALUE"""),"ultreyamarketing") -> ultreyamarketing | C81: =IFERROR(__xludf.DUMMYFUNCTION("""COMPUTED_VALUE"""),"sergipe.ofertas") -> sergipe.ofertas | D81: =IFERROR(__xludf.DUMMYFUNCTION("""COMPUTED_VALUE"""),100000) -> 100000
A82: =IFERROR(__xludf.DUMMYFUNCTION("""COMPUTED_VALUE"""),1435262807) -> 1435262807 | B82: =IFERROR(__xludf.DUMMYFUNCTION("""COMPUTED_VALUE"""),"tudonapromo") -> tudonapromo | C82: =IFERROR(__xludf.DUMMYFUNCTION("""COMPUTED_VALUE"""),"https://www.instagram.com/tuudonapromo") -> https://www.instagram.com/tuudonapromo | D82: =IFERROR(__xludf.DUMMYFUNCTION("""COMPUTED_VALUE"""),5828) -> 5828 | E82: =IFERROR(__xludf.DUMMYFUNCTION("""COMPUTED_VALUE"""),"https://www.tiktok.com/@tudonapromo_") -> https://www.tiktok.com/@tudonapromo_ | F82: =IFERROR(__xludf.DUMMYFUNCTION("""COMPUTED_VALUE"""),1000) -> 1000
A83: =IFERROR(__xludf.DUMMYFUNCTION("""COMPUTED_VALUE"""),255626570) -> 255626570 | B83: =IFERROR(__xludf.DUMMYFUNCTION("""COMPUTED_VALUE"""),"updesconto") -> updesconto | C83: =IFERROR(__xludf.DUMMYFUNCTION("""COMPUTED_VALUE"""),"www.instagram.com/updesconta") -> www.instagram.com/updesconta | D83: =IFERROR(__xludf.DUMMYFUNCTION("""COMPUTED_VALUE"""),20000) -> 20000
A84: =IFERROR(__xludf.DUMMYFUNCTION("""COMPUTED_VALUE"""),152436288) -> 152436288 | B84: =IFERROR(__xludf.DUMMYFUNCTION("""COMPUTED_VALUE"""),"gugaaprova") -> gugaaprova | C84: =IFERROR(__xludf.DUMMYFUNCTION("""COMPUTED_VALUE"""),"https://www.instagram.com/gugaaprova_/") -> https://www.instagram.com/gugaaprova_/ | D84: =IFERROR(__xludf.DUMMYFUNCTION("""COMPUTED_VALUE"""),19700) -> 19700 | E84: =IFERROR(__xludf.DUMMYFUNCTION("""COMPUTED_VALUE"""),"https://www.tiktok.com/@gugaetharcyla") -> https://www.tiktok.com/@gugaetharcyla | F84: =IFERROR(__xludf.DUMMYFUNCTION("""COMPUTED_VALUE"""),77600) -> 77600
A85: =IFERROR(__xludf.DUMMYFUNCTION("""COMPUTED_VALUE"""),2313173800) -> 2313173800 | B85: =IFERROR(__xludf.DUMMYFUNCTION("""COMPUTED_VALUE"""),"ofertinhasecia") -> ofertinhasecia | C85: =IFERROR(__xludf.DUMMYFUNCTION("""COMPUTED_VALUE"""),"") | D85: =IFERROR(__xludf.DUMMYFUNCTION("""COMPUTED_VALUE"""),"") | E85: =IFERROR(__xludf.DUMMYFUNCTION("""COMPUTED_VALUE"""),"") | F85: =IFERROR(__xludf.DUMMYFUNCTION("""COMPUTED_VALUE"""),"")
A86: =IFERROR(__xludf.DUMMYFUNCTION("""COMPUTED_VALUE"""),1365959356) -> 1365959356 | B86: =IFERROR(__xludf.DUMMYFUNCTION("""COMPUTED_VALUE"""),"adrenalinemc") -> adrenalinemc | C86: =IFERROR(__xludf.DUMMYFUNCTION("""COMPUTED_VALUE"""),"https://www.instagram.com/adrenaline_oficial/") -> https://www.instagram.com/adrenaline_oficial/ | D86: =IFERROR(__xludf.DUMMYFUNCTION("""COMPUTED_VALUE"""),248000) -> 248000 | E86: =IFERROR(__xludf.DUMMYFUNCTION("""COMPUTED_VALUE"""),"https://www.tiktok.com/@adrenalinecombr") -> https://www.tiktok.com/@adrenalinecombr | F86: =IFERROR(__xludf.DUMMYFUNCTION("""COMPUTED_VALUE"""),66200) -> 66200
A87: =IFERROR(__xludf.DUMMYFUNCTION("""COMPUTED_VALUE"""),379432988) -> 379432988 | B87: =IFERROR(__xludf.DUMMYFUNCTION("""COMPUTED_VALUE"""),"pmempdigitais") -> pmempdigitais | C87: =IFERROR(__xludf.DUMMYFUNCTION("""COMPUTED_VALUE"""),"https://www.instagram.com/paulodatecnologia/") -> https://www.instagram.com/paulodatecnologia/ | D87: =IFERROR(__xludf.DUMMYFUNCTION("""COMPUTED_VALUE"""),2200) -> 2200 | E87: =IFERROR(__xludf.DUMMYFUNCTION("""COMPUTED_VALUE"""),"https://www.tiktok.com/@paulodatecnologia") -> https://www.tiktok.com/@paulodatecnologia | F87: =IFERROR(__xludf.DUMMYFUNCTION("""COMPUTED_VALUE"""),6500) -> 6500
A88: =IFERROR(__xludf.DUMMYFUNCTION("""COMPUTED_VALUE"""),547239300) -> 547239300 | B88: =IFERROR(__xludf.DUMMYFUNCTION("""COMPUTED_VALUE"""),"d6news") -> d6news | C88: =IFERROR(__xludf.DUMMYFUNCTION("""COMPUTED_VALUE"""),"https://www.instagram.com/manualdecompra/") -> https://www.instagram.com/manualdecompra/ | D88: =IFERROR(__xludf.DUMMYFUNCTION("""COMPUTED_VALUE"""),106) -> 106 | E88: =IFERROR(__xludf.DUMMYFUNCTION("""COMPUTED_VALUE"""),"https://www.tiktok.com/@manual.de.compra") -> https://www.tiktok.com/@manual.de.compra | F88: =IFERROR(__xludf.DUMMYFUNCTION("""COMPUTED_VALUE"""),26) -> 26
A89: =IFERROR(__xludf.DUMMYFUNCTION("""COMPUTED_VALUE"""),1343085375) -> 1343085375 | B89: =IFERROR(__xludf.DUMMYFUNCTION("""COMPUTED_VALUE"""),"felps") -> felps | C89: =IFERROR(__xludf.DUMMYFUNCTION("""COMPUTED_VALUE"""),"https://www.instagram.com/felps?igsh=NGh1NnhxeXF3ZjBi&utm_source=qr") -> https://www.instagram.com/felps?igsh=NGh1NnhxeXF3ZjBi&utm_source=qr | D89: =IFERROR(__xludf.DUMMYFUNCTION("""COMPUTED_VALUE"""),71300) -> 71300 | E89: =IFERROR(__xludf.DUMMYFUNCTION("""COMPUTED_VALUE"""),"https://www.tiktok.com/@felpstech?_t=ZM-8ydRaxH76b0&_r=1") -> https://www.tiktok.com/@felpstech?_t=ZM-8ydRaxH76b0&_r=1 | F89: =IFERROR(__xludf.DUMMYFUNCTION("""COMPUTED_VALUE"""),60600) -> 60600
A90: =IFERROR(__xludf.DUMMYFUNCTION("""COMPUTED_VALUE"""),323819368) -> 323819368 | B90: =IFERROR(__xludf.DUMMYFUNCTION("""COMPUTED_VALUE"""),"alupa") -> alupa | C90: =IFERROR(__xludf.DUMMYFUNCTION("""COMPUTED_VALUE"""),"https://www.instagram.com/alupaofertas") -> https://www.instagram.com/alupaofertas | D90: =IFERROR(__xludf.DUMMYFUNCTION("""COMPUTED_VALUE"""),5000) -> 5000
A91: =IFERROR(__xludf.DUMMYFUNCTION("""COMPUTED_VALUE"""),1416008866) -> 1416008866 | B91: =IFERROR(__xludf.DUMMYFUNCTION("""COMPUTED_VALUE"""),"superconsumer23") -> superconsumer23 | C91: =IFERROR(__xludf.DUMMYFUNCTION("""COMPUTED_VALUE"""),"https://www.instagram.com/superconsumer_?igsh=MWVhZGExbjc5dGN0MQ%3D%3D&utm_source=qr") -> https://www.instagram.com/superconsumer_?igsh=MWVhZGExbjc5dGN0MQ%3D%3D&utm_source=qr | D91: =IFERROR(__xludf.DUMMYFUNCTION("""COMPUTED_VALUE"""),17000) -> 17000 | E91: =IFERROR(__xludf.DUMMYFUNCTION("""COMPUTED_VALUE"""),"https://www.tiktok.com/@superconsumer?_t=ZM-8yzM19UwYQ1&_r=1") -> https://www.tiktok.com/@superconsumer?_t=ZM-8yzM19UwYQ1&_r=1 | F91: =IFERROR(__xludf.DUMMYFUNCTION("""COMPUTED_VALUE"""),5600) -> 5600
A92: =IFERROR(__xludf.DUMMYFUNCTION("""COMPUTED_VALUE"""),134739278) -> 134739278 | B92: =IFERROR(__xludf.DUMMYFUNCTION("""COMPUTED_VALUE"""),"cmdias") -> cmdias | C92: =IFERROR(__xludf.DUMMYFUNCTION("""COMPUTED_VALUE"""),"https://www.instagram.com/cmdias_oficial?igsh=MXhkazV4a3ZvOGF2cg%3D%3D&utm_source=qr") -> https://www.instagram.com/cmdias_oficial?igsh=MXhkazV4a3ZvOGF2cg%3D%3D&utm_source=qr | D92: =IFERROR(__xludf.DUMMYFUNCTION("""COMPUTED_VALUE"""),3200) -> 3200 | E92: =IFERROR(__xludf.DUMMYFUNCTION("""COMPUTED_VALUE"""),"https://www.tiktok.com/@cmdias_oficial?_t=ZM-8yncuV98E6S&_r=1") -> https://www.tiktok.com/@cmdias_oficial?_t=ZM-8yncuV98E6S&_r=1 | F92: =IFERROR(__xludf.DUMMYFUNCTION("""COMPUTED_VALUE"""),5000) -> 5000
A93: =IFERROR(__xludf.DUMMYFUNCTION("""COMPUTED_VALUE"""),1885573171) -> 1885573171 | B93: =IFERROR(__xludf.DUMMYFUNCTION("""COMPUTED_VALUE"""),"talkpcx") -> talkpcx | C93: =IFERROR(__xludf.DUMMYFUNCTION("""COMPUTED_VALUE"""),"https://www.instagram.com/vitordobranding") -> https://www.instagram.com/vitordobranding | D93: =IFERROR(__xludf.DUMMYFUNCTION("""COMPUTED_VALUE"""),500) -> 500 | E93: =IFERROR(__xludf.DUMMYFUNCTION("""COMPUTED_VALUE"""),"https://www.tiktok.com/@talk.pc?_t=ZM-8wlznUJVtGI&_r=1") -> https://www.tiktok.com/@talk.pc?_t=ZM-8wlznUJVtGI&_r=1 | F93: =IFERROR(__xludf.DUMMYFUNCTION("""COMPUTED_VALUE"""),350) -> 350
A94: =IFERROR(__xludf.DUMMYFUNCTION("""COMPUTED_VALUE"""),286249876) -> 286249876 | B94: =IFERROR(__xludf.DUMMYFUNCTION("""COMPUTED_VALUE"""),"acheinapromo") -> acheinapromo | C94: =IFERROR(__xludf.DUMMYFUNCTION("""COMPUTED_VALUE"""),"https://www.instagram.com/acheinapromoo/") -> https://www.instagram.com/acheinapromoo/ | D94: =IFERROR(__xludf.DUMMYFUNCTION("""COMPUTED_VALUE"""),115) -> 115 | E94: =IFERROR(__xludf.DUMMYFUNCTION("""COMPUTED_VALUE"""),"https://www.tiktok.com/@juliafarath") -> https://www.tiktok.com/@juliafarath | F94: =IFERROR(__xludf.DUMMYFUNCTION("""COMPUTED_VALUE"""),18) -> 18
A95: =IFERROR(__xludf.DUMMYFUNCTION("""COMPUTED_VALUE"""),1494770433) -> 1494770433 | B95: =IFERROR(__xludf.DUMMYFUNCTION("""COMPUTED_VALUE"""),"gabpromo") -> gabpromo | C95: =IFERROR(__xludf.DUMMYFUNCTION("""COMPUTED_VALUE"""),"https://www.instagram.com/gabpromo_/") -> https://www.instagram.com/gabpromo_/ | D95: =IFERROR(__xludf.DUMMYFUNCTION("""COMPUTED_VALUE"""),8800) -> 8800 | E95: =IFERROR(__xludf.DUMMYFUNCTION("""COMPUTED_VALUE"""),"https://www.tiktok.com/@gabpromo_") -> https://www.tiktok.com/@gabpromo_ | F95: =IFERROR(__xludf.DUMMYFUNCTION("""COMPUTED_VALUE"""),1100) -> 1100
A96: =IFERROR(__xludf.DUMMYFUNCTION("""COMPUTED_VALUE"""),1291850544) -> 1291850544 | B96: =IFERROR(__xludf.DUMMYFUNCTION("""COMPUTED_VALUE"""),"compreibarato") -> compreibarato | C96: =IFERROR(__xludf.DUMMYFUNCTION("""COMPUTED_VALUE"""),"https://www.instagram.com/achadosebarato?igsh=Nmh4YzU2ZmxqMHd2&utm_source=qr") -> https://www.instagram.com/achadosebarato?igsh=Nmh4YzU2ZmxqMHd2&utm_source=qr | D96: =IFERROR(__xludf.DUMMYFUNCTION("""COMPUTED_VALUE"""),7800) -> 7800
A97: =IFERROR(__xludf.DUMMYFUNCTION("""COMPUTED_VALUE"""),1224327239) -> 1224327239 | B97: =IFERROR(__xludf.DUMMYFUNCTION("""COMPUTED_VALUE"""),"cardosohenrique20230309120708") -> cardosohenrique20230309120708 | C97: =IFERROR(__xludf.DUMMYFUNCTION("""COMPUTED_VALUE"""),"https://www.instagram.com/henriquecardosoyt/") -> https://www.instagram.com/henriquecardosoyt/ | D97: =IFERROR(__xludf.DUMMYFUNCTION("""COMPUTED_VALUE"""),2000) -> 2000 | E97: =IFERROR(__xludf.DUMMYFUNCTION("""COMPUTED_VALUE"""),"https://www.tiktok.com/@henriquecardosotech") -> https://www.tiktok.com/@henriquecardosotech | F97: =IFERROR(__xludf.DUMMYFUNCTION("""COMPUTED_VALUE"""),1000) -> 1000
A98: =IFERROR(__xludf.DUMMYFUNCTION("""COMPUTED_VALUE"""),56905243) -> 56905243 | B98: =IFERROR(__xludf.DUMMYFUNCTION("""COMPUTED_VALUE"""),"tudoporumdesconto") -> tudoporumdesconto | C98: =IFERROR(__xludf.DUMMYFUNCTION("""COMPUTED_VALUE"""),"") | D98: =IFERROR(__xludf.DUMMYFUNCTION("""COMPUTED_VALUE"""),"") | E98: =IFERROR(__xludf.DUMMYFUNCTION("""COMPUTED_VALUE"""),"") | F98: =IFERROR(__xludf.DUMMYFUNCTION("""COMPUTED_VALUE"""),"")
A99: =IFERROR(__xludf.DUMMYFUNCTION("""COMPUTED_VALUE"""),138261262) -> 138261262 | B99: =IFERROR(__xludf.DUMMYFUNCTION("""COMPUTED_VALUE"""),"tecnan") -> tecnan | C99: =IFERROR(__xludf.DUMMYFUNCTION("""COMPUTED_VALUE"""),"https://www.instagram.com/tecnan_informatica") -> https://www.instagram.com/tecnan_informatica | D99: =IFERROR(__xludf.DUMMYFUNCTION("""COMPUTED_VALUE"""),24000) -> 24000 | E99: =IFERROR(__xludf.DUMMYFUNCTION("""COMPUTED_VALUE"""),"https://www.tiktok.com/@tecnaninformatica") -> https://www.tiktok.com/@tecnaninformatica | F99: =IFERROR(__xludf.DUMMYFUNCTION("""COMPUTED_VALUE"""),81000) -> 81000
A100: =IFERROR(__xludf.DUMMYFUNCTION("""COMPUTED_VALUE"""),202022997) -> 202022997 | B100: =IFERROR(__xludf.DUMMYFUNCTION("""COMPUTED_VALUE"""),"technatela") -> technatela | C100: =IFERROR(__xludf.DUMMYFUNCTION("""COMPUTED_VALUE"""),"https://www.instagram.com/technatela/") -> https://www.instagram.com/technatela/ | D100: =IFERROR(__xludf.DUMMYFUNCTION("""COMPUTED_VALUE"""),272000) -> 272000 | E100: =IFERROR(__xludf.DUMMYFUNCTION("""COMPUTED_VALUE"""),"https://www.tiktok.com/@technatela") -> https://www.tiktok.com/@technatela | F100: =IFERROR(__xludf.DUMMYFUNCTION("""COMPUTED_VALUE"""),158000) -> 158000
...
